{
  "id": 429,
  "key": "Kalista",
  "name": "Kalista",
  "title": "the Spear of Vengeance",
  "fullName": "",
  "icon": "http://ddragon.leagueoflegends.com/cdn/14.7.1/img/champion/Kalista.png",
  "resource": "MANA",
  "attackType": "RANGED",
  "adaptiveType": "PHYSICAL_DAMAGE",
  "stats": {
    "health": {
      "flat": 600,
      "percent": 0,
      "perLevel": 114,
      "percentPerLevel": 0
    },
    "healthRegen": {
      "flat": 4,
      "percent": 0,
      "perLevel": 0.75,
      "percentPerLevel": 0
    },
    "mana": {
      "flat": 300,
      "percent": 0,
      "perLevel": 45,
      "percentPerLevel": 0
    },
    "manaRegen": {
      "flat": 6.3,
      "percent": 0,
      "perLevel": 0.4,
      "percentPerLevel": 0
    },
    "armor": {
      "flat": 24,
      "percent": 0,
      "perLevel": 5.2,
      "percentPerLevel": 0
    },
    "magicResistance": {
      "flat": 30,
      "percent": 0,
      "perLevel": 1.3,
      "percentPerLevel": 0
    },
    "attackDamage": {
      "flat": 61,
      "percent": 0,
      "perLevel": 3.25,
      "percentPerLevel": 0
    },
    "movespeed": {
      "flat": 330,
      "percent": 0,
      "perLevel": 0,
      "percentPerLevel": 0
    },
    "acquisitionRadius": {
      "flat": 900,
      "percent": 0,
      "perLevel": 0,
      "percentPerLevel": 0
    },
    "selectionRadius": {
      "flat": 100,
      "percent": 0,
      "perLevel": 0,
      "percentPerLevel": 0
    },
    "pathingRadius": {
      "flat": 35,
      "percent": 0,
      "perLevel": 0,
      "percentPerLevel": 0
    },
    "gameplayRadius": {
      "flat": 65,
      "percent": 0,
      "perLevel": 0,
      "percentPerLevel": 0
    },
    "criticalStrikeDamage": {
      "flat": 175,
      "percent": 0,
      "perLevel": 0,
      "percentPerLevel": 0
    },
    "criticalStrikeDamageModifier": {
      "flat": 1,
      "percent": 0,
      "perLevel": 0,
      "percentPerLevel": 0
    },
    "attackSpeed": {
      "flat": 0.694,
      "percent": 0,
      "perLevel": 4.5,
      "percentPerLevel": 0
    },
    "attackSpeedRatio": {
      "flat": 0.694000005722045,
      "percent": 0,
      "perLevel": 0,
      "percentPerLevel": 0
    },
    "attackCastTime": {
      "flat": 0.3,
      "percent": 0,
      "perLevel": 0,
      "percentPerLevel": 0
    },
    "attackTotalTime": {
      "flat": 1.6,
      "percent": 0,
      "perLevel": 0,
      "percentPerLevel": 0
    },
    "attackDelayOffset": {
      "flat": 0.0599999986588954,
      "percent": 0,
      "perLevel": 0,
      "percentPerLevel": 0
    },
    "attackRange": {
      "flat": 525,
      "percent": 0,
      "perLevel": 0,
      "percentPerLevel": 0
    },
    "aramDamageTaken": {
      "flat": 0.9,
      "percent": 0,
      "perLevel": 0,
      "percentPerLevel": 0
    },
    "aramDamageDealt": {
      "flat": 1.1,
      "percent": 0,
      "perLevel": 0,
      "percentPerLevel": 0
    },
    "aramHealing": {
      "flat": 1,
      "percent": 0,
      "perLevel": 0,
      "percentPerLevel": 0
    },
    "aramShielding": {
      "flat": 1,
      "percent": 0,
      "perLevel": 0,
      "percentPerLevel": 0
    },
    "urfDamageTaken": {
      "flat": 0.9,
      "percent": 0,
      "perLevel": 0,
      "percentPerLevel": 0
    },
    "urfDamageDealt": {
      "flat": 1.1,
      "percent": 0,
      "perLevel": 0,
      "percentPerLevel": 0
    },
    "urfHealing": {
      "flat": 1,
      "percent": 0,
      "perLevel": 0,
      "percentPerLevel": 0
    },
    "urfShielding": {
      "flat": 1,
      "percent": 0,
      "perLevel": 0,
      "percentPerLevel": 0
    }
  },
  "roles": [
    "MARKSMAN"
  ],
  "attributeRatings": {
    "damage": 3,
    "toughness": 1,
    "control": 1,
    "mobility": 3,
    "utility": 2,
    "abilityReliance": 10,
    "difficulty": 3
  },
  "abilities": {
    "P": [
      {
        "name": "Martial Poise",
        "icon": "https://cdn.communitydragon.org/latest/champion/Kalista/ability-icon/p",
        "effects": [
          {
            "description": "Innate: Whenever Kalista inputs a movement command during her basic attack windup or the cast time of Pierce, she will dash in the target direction.Kalista's dash from Martial Poise will be knocked down by any immobilizing or polymorphing crowd control, excluding sleep(bug).",
            "leveling": []
          },
          {
            "description": "The range and speed of Martial Poise are modified by the tier of Kalista's Boots. The base range when dashing from a basic attack is 250 / 265 / 280 (based on Boots Tier) units. This base distance is reduced when dashing toward the direction of her attack, to a minimum of 150 / 165 / 180 (based on Boots Tier) units.",
            "leveling": []
          },
          {
            "description": "The base range when dashing from Pierce's cast is increased[ by 50 units. ][ to 300 / 315 / 330 (based on Boots Tier) units. ]If dashing away from the point of cast, the dash range is reduced, to a minimum of 165 / 180 / 195 (based on Boots Tier) units.",
            "leveling": []
          },
          {
            "description": "Innate - Oathsworn Bond: Kalista begins the game with an exclusive Black Spear.",
            "leveling": []
          }
        ],
        "cost": null,
        "cooldown": null,
        "targeting": "Direction",
        "affects": "Self",
        "spellshieldable": null,
        "resource": null,
        "damageType": null,
        "spellEffects": null,
        "projectile": null,
        "onHitEffects": null,
        "occurrence": null,
        "notes": "There is a very brief grace period in excess of the on-screen timers wherein Kalista can still trigger Martial Poise.\nThe dash speed depends on Kalista's bonus attack speed and Boots Tier. Basic boots increase the dash speed by 75, and Finished boots increase it by 135.\nThe dash speed is affected by  multiplicative movement speed modifiers such as  slows.\n Additive movement speed modifiers do not affect it.\nThere are a total of 24 different dash ranges based on direction with Boots and  Pierce being cast.\nDash distance decreases exponentially as the dash direction becomes closer to the minimum direction (forward for basic attacks, backward for  Pierce.\nKalista will attempt to attack her target again at the end of the dash, allowing the player to kite with only movement commands as long as they remain in attack range.\nAttack move click checks for targets in brief intervals, but only while Kalista is not in a dash, resulting in lost DPS if it is used to automatically dash.\nKalista's facing direction when dashing is considered to be in the direction of the dash, not her visual facing direction.",
        "blurb": "Innate: During each basic attack or  Pierce,  Kalista can choose a target direction to quickly  dash to. The range and speed is based on the tier of Kalista's Boots.",
        "missileSpeed": null,
        "rechargeRate": null,
        "collisionRadius": null,
        "tetherRadius": null,
        "onTargetCdStatic": null,
        "innerRadius": null,
        "speed": "1025 / 1100 / 1160 (based on Boots Tier)",
        "width": null,
        "angle": null,
        "castTime": null,
        "effectRadius": null,
        "targetRange": "250 / 265 / 280 (based on Boots Tier)"
      }
    ],
    "Q": [
      {
        "name": "Pierce",
        "icon": "https://cdn.communitydragon.org/latest/champion/Kalista/ability-icon/q",
        "effects": [
          {
            "description": "Active: Kalista launches a spear in the target direction that deals physical damage to the first enemy hit.",
            "leveling": [
              {
                "attribute": "Physical Damage",
                "modifiers": [
                  {
                    "values": [
                      20,
                      85,
                      150,
                      215,
                      280
                    ],
                    "units": [
                      "",
                      "",
                      "",
                      "",
                      ""
                    ]
                  },
                  {
                    "values": [
                      105,
                      105,
                      105,
                      105,
                      105
                    ],
                    "units": [
                      "% AD",
                      "% AD",
                      "% AD",
                      "% AD",
                      "% AD"
                    ]
                  }
                ]
              }
            ]
          },
          {
            "description": "If Pierce kills the target, the spear continues onward to transfer all of the target's Rend stacks to the next enemy it hits. This can repeat indefinitely until the spear reaches its maximum range.",
            "leveling": []
          }
        ],
        "cost": {
          "modifiers": [
            {
              "values": [
                50,
                55,
                60,
                65,
                70
              ],
              "units": [
                "",
                "",
                "",
                "",
                ""
              ]
            }
          ]
        },
        "cooldown": {
          "modifiers": [
            {
              "values": [
                8,
                8,
                8,
                8,
                8
              ],
              "units": [
                "",
                "",
                "",
                "",
                ""
              ]
            }
          ],
          "affectedByCdr": true
        },
        "targeting": "Direction",
        "affects": "Enemies",
        "spellshieldable": "True",
        "resource": "MANA",
        "damageType": "PHYSICAL_DAMAGE",
        "spellEffects": "Single target",
        "projectile": "TRUE",
        "onHitEffects": null,
        "occurrence": null,
        "notes": "This ability will cast from wherever the caster is at the end of the cast time.",
        "blurb": "Active:  Kalista throws a spear in the target direction that deals physical damage to the first enemy hit.",
        "missileSpeed": null,
        "rechargeRate": null,
        "collisionRadius": null,
        "tetherRadius": null,
        "onTargetCdStatic": null,
        "innerRadius": null,
        "speed": "2400",
        "width": "80",
        "angle": null,
        "castTime": "0.25",
        "effectRadius": null,
        "targetRange": "1200"
      }
    ],
    "W": [
      {
        "name": "Sentinel",
        "icon": "https://cdn.communitydragon.org/latest/champion/Kalista/ability-icon/w",
        "effects": [
          {
            "description": "Passive - Soul-Marked: While Kalista and her Oathsworn are tethered, their basic attacks and Pierce apply a Soul-Mark to their targets.",
            "leveling": []
          },
          {
            "description": "If both Soul-Marks are applied to the same target within 4 seconds, they take bonus magic damage, capped against non-champions, and cannot be Soul-Marked again for a few seconds. Soul-Mark deals a minimum of 75 damage to minions, executes them if they're below 125 health, and is capped against non-champions. Kalista applies the damage on-attack while the Oathsworn does so on-hit.",
            "leveling": [
              {
                "attribute": "Bonus Magic Damage",
                "modifiers": [
                  {
                    "values": [
                      14,
                      15,
                      16,
                      17,
                      18
                    ],
                    "units": [
                      "% of target's maximum health",
                      "% of target's maximum health",
                      "% of target's maximum health",
                      "% of target's maximum health",
                      "% of target's maximum health"
                    ]
                  }
                ]
              },
              {
                "attribute": "Maximum Non-Champion Damage",
                "modifiers": [
                  {
                    "values": [
                      100,
                      125,
                      150,
                      175,
                      200
                    ],
                    "units": [
                      "",
                      "",
                      "",
                      "",
                      ""
                    ]
                  }
                ]
              }
            ]
          },
          {
            "description": "Active: Kalista summons a Sentinel that patrols back and forth on a path along the target location, granting sight of its surroundings as it travels.",
            "leveling": []
          },
          {
            "description": "Kalista periodically stocks a Sentinel charge, up to a maximum of 2.",
            "leveling": []
          },
          {
            "description": "See Pets for more details about Sentinels.",
            "leveling": []
          }
        ],
        "cost": null,
        "cooldown": {
          "modifiers": [
            {
              "values": [
                30,
                30,
                30,
                30,
                30
              ],
              "units": [
                "",
                "",
                "",
                "",
                ""
              ]
            }
          ],
          "affectedByCdr": true
        },
        "targeting": "Direction",
        "affects": "Enemies",
        "spellshieldable": null,
        "resource": null,
        "damageType": "MAGIC_DAMAGE",
        "spellEffects": "proc",
        "projectile": null,
        "onHitEffects": null,
        "occurrence": null,
        "notes": "Soul-Marked's bonus damage is credited to Kalista and will benefit from both her  magic penetration and spell effects.\nIf her  Oathsworn ally scores a kill using Soul-Marked's bonus damage they will get a message stating 'Kill Secured' in place of the usual gold pop-up (the gold itself is credited to Kalista).\nThe Sentinel's  sight reveal on enemy  champions is accredited for assists and potentially kills (if they die shortly after being spotted).\nIt does not reveal  stealthed targets.\nSentinel will cast from wherever Kalista is at the end of the cast time.\n PENDING FOR TEST:: Soul Mark's interaction with parrying effects ( dodge,  block,  blind).\n PENDING FOR TEST: If Pierce kills the target by Soul-Mark's additional damage, it will/will not continue.",
        "blurb": "Passive - Soul-Marked: While  Kalista and her  Oathsworn are  tethered, their basic attacks and  Pierce apply a Soul-Mark to their targets. If both Soul-Marks are applied to the same target within a few seconds, they take bonus magic damage.",
        "missileSpeed": null,
        "rechargeRate": [
          90,
          80,
          70,
          60,
          50
        ],
        "collisionRadius": null,
        "tetherRadius": "1100",
        "onTargetCdStatic": "10",
        "innerRadius": null,
        "speed": null,
        "width": null,
        "angle": null,
        "castTime": "0.5",
        "effectRadius": null,
        "targetRange": "1400 / 5000"
      }
    ],
    "E": [
      {
        "name": "Rend",
        "icon": "https://cdn.communitydragon.org/latest/champion/Kalista/ability-icon/e",
        "effects": [
          {
            "description": "Passive: Kalista's basic attacks on-hit and Pierce apply a stack of Rend to enemies for 4 seconds, refreshing on subsequent hits and stacking up to 254 times.",
            "leveling": []
          },
          {
            "description": "Active: Kalista rips all lodged spears from nearby enemies, consuming all of their stacks to deal them physical damage and slow them for 2 seconds. Each additional spear on the target deals reduced damage. Rend deals 50% reduced damage against epic monsters.",
            "leveling": [
              {
                "attribute": "Physical Damage",
                "modifiers": [
                  {
                    "values": [
                      10,
                      20,
                      30,
                      40,
                      50
                    ],
                    "units": [
                      "",
                      "",
                      "",
                      "",
                      ""
                    ]
                  },
                  {
                    "values": [
                      70,
                      70,
                      70,
                      70,
                      70
                    ],
                    "units": [
                      "% AD",
                      "% AD",
                      "% AD",
                      "% AD",
                      "% AD"
                    ]
                  },
                  {
                    "values": [
                      20,
                      20,
                      20,
                      20,
                      20
                    ],
                    "units": [
                      "% AP",
                      "% AP",
                      "% AP",
                      "% AP",
                      "% AP"
                    ]
                  }
                ]
              },
              {
                "attribute": "Damage per Additional Stack",
                "modifiers": [
                  {
                    "values": [
                      8,
                      12,
                      16,
                      20,
                      24
                    ],
                    "units": [
                      "",
                      "",
                      "",
                      "",
                      ""
                    ]
                  },
                  {
                    "values": [
                      25,
                      30,
                      35,
                      40,
                      45
                    ],
                    "units": [
                      "% AD",
                      "% AD",
                      "% AD",
                      "% AD",
                      "% AD"
                    ]
                  },
                  {
                    "values": [
                      20,
                      20,
                      20,
                      20,
                      20
                    ],
                    "units": [
                      "% AP",
                      "% AP",
                      "% AP",
                      "% AP",
                      "% AP"
                    ]
                  }
                ]
              },
              {
                "attribute": "Slow",
                "modifiers": [
                  {
                    "values": [
                      10,
                      18,
                      26,
                      34,
                      42
                    ],
                    "units": [
                      "%",
                      "%",
                      "%",
                      "%",
                      "%"
                    ]
                  },
                  {
                    "values": [
                      5,
                      5,
                      5,
                      5,
                      5
                    ],
                    "units": [
                      "% per 100 AP",
                      "% per 100 AP",
                      "% per 100 AP",
                      "% per 100 AP",
                      "% per 100 AP"
                    ]
                  }
                ]
              }
            ]
          },
          {
            "description": "If Rend kills at least one target, the cooldown is reset and Kalista restores mana.",
            "leveling": [
              {
                "attribute": "Mana Restored",
                "modifiers": [
                  {
                    "values": [
                      10,
                      15,
                      20,
                      25,
                      30
                    ],
                    "units": [
                      "",
                      "",
                      "",
                      "",
                      ""
                    ]
                  }
                ]
              }
            ]
          },
          {
            "description": "A nearby enemy with a Rend stack is required to cast this ability. Rend can be used during the dash of Martial Poise and the cast time of Pierce. In-flight spears and Pierce if in cast will be empowered to apply Rend's effects to their targets. These empowered spears can also trigger Rend's refund.",
            "leveling": []
          }
        ],
        "cost": {
          "modifiers": [
            {
              "values": [
                30,
                30,
                30,
                30,
                30
              ],
              "units": [
                "",
                "",
                "",
                "",
                ""
              ]
            }
          ]
        },
        "cooldown": {
          "modifiers": [
            {
              "values": [
                10,
                9.5,
                9,
                8.5,
                8
              ],
              "units": [
                "",
                "",
                "",
                "",
                ""
              ]
            }
          ],
          "affectedByCdr": true
        },
        "targeting": "Auto",
        "affects": "Enemies",
        "spellshieldable": "True",
        "resource": "MANA",
        "damageType": "PHYSICAL_DAMAGE",
        "spellEffects": "Area of effect",
        "projectile": null,
        "onHitEffects": null,
        "occurrence": null,
        "notes": "Rend at maximum stacks will deal a total of 2044 / 3066 / 4341 / 5869 / 7650 (+ 5914.3 / 7079.618 / 8186.493 / 9293.368 / 10400.243% AD) physical damage.\nRend cannot activate on  untargetable enemies.\nRend applies its effects instantly on cast.\nThe cooldown will not reset if the target is protected by  resurrection effects.\nIf Rend is used against  Sion under the effects of  Glory in Death, the cooldown will reset even if it does not kill him.(bug)\nA stack is not applied if the attack is  dodged,  blocked or missed while Kalista is  blinded.\n Pierce does not apply a stack of Rend if blocked by  spell shield.\nWhile  beserk, Kalista's attacks will also stack Rend on allies.\nKalista will be unable to cast Rend if there are no stacks on an enemy in range.\nRend will only remove enemy spears if cast while both an ally and enemy with stacks are in range.",
        "blurb": "Passive: Kalista's basic attacks and  Pierce lodge a spear into their target, applying a stack of Rend for a few seconds.",
        "missileSpeed": null,
        "rechargeRate": null,
        "collisionRadius": null,
        "tetherRadius": null,
        "onTargetCdStatic": null,
        "innerRadius": null,
        "speed": null,
        "width": null,
        "angle": null,
        "castTime": "0.25",
        "effectRadius": "1100",
        "targetRange": null
      }
    ],
    "R": [
      {
        "name": "Fate's Call",
        "icon": "https://cdn.communitydragon.org/latest/champion/Kalista/ability-icon/r",
        "effects": [
          {
            "description": "Active: Kalista invokes her tether to retrieve and hold her Oathsworn for 4 seconds. Kalista cleanses the Oathsworn from all crowd control and renders them invulnerable and untargetable for the duration, and pulls them to her over 1 second.",
            "leveling": []
          },
          {
            "description": "While held, the Oathsworn is vanished and may select to end Fate's Call's invocation and dash with displacement immunity, reappearing at the target location, and doing so at maximum range from Kalista's facing direction when the duration expires. The Oathsworn stops upon colliding with an enemy champion, knocking up all nearby enemies for a duration and finally landing to their base attack range from the target collided with.",
            "leveling": [
              {
                "attribute": "Knockup Duration",
                "modifiers": [
                  {
                    "values": [
                      1,
                      1.5,
                      2
                    ],
                    "units": [
                      "",
                      "",
                      ""
                    ]
                  }
                ]
              }
            ]
          },
          {
            "description": "The Oathsworn must be nearby to cast this ability, and is also silenced and unable to perform movement or attack commands while Fate's Call is in effect.",
            "leveling": []
          }
        ],
        "cost": {
          "modifiers": [
            {
              "values": [
                100,
                100,
                100
              ],
              "units": [
                "",
                "",
                ""
              ]
            }
          ]
        },
        "cooldown": {
          "modifiers": [
            {
              "values": [
                150,
                120,
                90
              ],
              "units": [
                "",
                "",
                ""
              ]
            }
          ],
          "affectedByCdr": true
        },
        "targeting": "Auto",
        "affects": "Oathsworn Ally / Enemies",
        "spellshieldable": "True",
        "resource": "MANA",
        "damageType": null,
        "spellEffects": "False",
        "projectile": null,
        "onHitEffects": null,
        "occurrence": null,
        "notes": "The following will defer Fate's Call's effects at the time of cast to the end of their duration if the Oathsworn is:\nIn a cast time.\n Channeling.\nFate's Call will not defer by the following channels:  Recall,  Defiant Dance,  Realm Warp, and  The Culling.\nFate's Call cannot be cast during the following channels:  Teleport,  Gate,  Grand Starfall,  Hero's Entrance and  Stand United.\nUsing an ability that preloads UnstoppableForceMarker.\nIf the Oathsworn is still occupied after 6 seconds of being deferred from this time, Fate's Call will cancel.\nFate's Call will not pull the Oathsworn if they are  dashing but they will be retrieved after 1 second regardless.\nFate's Call can be cast even if the Oathsworn is  untargetable.\nFate's Call is disabled if the Oathsworn is  resurrecting or is being affected by another Fate's Call.\nFate's Call can be used even if the Oathsworn is in a  zombie state.\nFate's Call does not render the target  vanished while being held if they are creating  Curse of the Black Mist's aura.\nThe Oathsworn being held is represented by a light over Kalista's head.\nKalista's death does not cancel Fate's Call.",
        "blurb": "Active:  Kalista invokes her  tether to retrieve her Oathsworn,  vanishing and  cleansing them from all  crowd control, and hold them for a few seconds.",
        "missileSpeed": null,
        "rechargeRate": null,
        "collisionRadius": null,
        "tetherRadius": "1100",
        "onTargetCdStatic": null,
        "innerRadius": null,
        "speed": null,
        "width": null,
        "angle": null,
        "castTime": "none",
        "effectRadius": null,
        "targetRange": "1200"
      }
    ]
  },
  "releaseDate": "2014-11-20",
  "releasePatch": "4.20",
  "patchLastChanged": "14.4",
  "price": {
    "blueEssence": 4800,
    "rp": 880,
    "saleRp": 0
  },
  "lore": "A specter of wrath and retribution, Kalista is the undying spirit of vengeance, an armored nightmare summoned from the Shadow Isles to hunt deceivers and traitors. The betrayed may cry out in blood to be avenged, but Kalista only answers those willing to pay with their very souls. Those who become the focus of Kalista's wrath should make their final peace, for any pact sealed with this grim hunter can only end with the cold, piercing fire of her soul-spears.",
  "faction": "shadow-isles",
  "skins": [
    {
      "name": "Original",
      "id": 429000,
      "isBase": true,
      "availability": "Available",
      "formatName": "Original",
      "lootEligible": true,
      "cost": 880,
      "sale": 0,
      "distribution": null,
      "rarity": "NoRarity",
      "chromas": [],
      "lore": "A specter of wrath and retribution, Kalista is the undying spirit of vengeance, an armored nightmare summoned from the Shadow Isles to hunt deceivers and traitors. The betrayed may cry out in blood to be avenged, but Kalista only answers those willing to pay with their very souls. Those who become the focus of Kalista’s wrath should make their final peace, for any pact sealed with this grim hunter can only end with the cold, piercing fire of her soul-spears.",
      "release": "2014-11-20",
      "set": [],
      "splashPath": "http://raw.communitydragon.org/pbe/plugins/rcp-be-lol-game-data/global/default/v1/champion-splashes/429/429000.jpg",
      "uncenteredSplashPath": "http://raw.communitydragon.org/pbe/plugins/rcp-be-lol-game-data/global/default/v1/champion-splashes/uncentered/429/429000.jpg",
      "tilePath": "http://raw.communitydragon.org/pbe/plugins/rcp-be-lol-game-data/global/default/v1/champion-tiles/429/429000.jpg",
      "loadScreenPath": "https://raw.communitydragon.org/pbe/plugins/rcp-be-lol-game-data/global/default/assets/characters/kalista/skins/base/kalistaloadscreen.jpg",
      "loadScreenVintagePath": null,
      "newEffects": false,
      "newAnimations": false,
      "newRecall": false,
      "newVoice": false,
      "newQuotes": false,
      "voiceActor": [
        "Misty Lee"
      ],
      "splashArtist": [
        "Pan Chengwei"
      ]
    },
    {
      "name": "Blood Moon",
      "id": 429001,
      "isBase": false,
      "availability": "Available",
      "formatName": "Blood Moon",
      "lootEligible": true,
      "cost": 975,
      "sale": 0,
      "distribution": null,
      "rarity": "NoRarity",
      "chromas": [],
      "lore": "A demon of vengeance summoned on the night of the Blood Moon, Kalista's singular obsession with 'betrayers' knows no limits—any deception, no matter how trivial, will be met with death. Her victims are left hanging from the walls of their homes, a warning to those who remain.",
      "release": "2014-11-20",
      "set": [
        "Blood Moon"
      ],
      "splashPath": "http://raw.communitydragon.org/pbe/plugins/rcp-be-lol-game-data/global/default/v1/champion-splashes/429/429001.jpg",
      "uncenteredSplashPath": "http://raw.communitydragon.org/pbe/plugins/rcp-be-lol-game-data/global/default/v1/champion-splashes/uncentered/429/429001.jpg",
      "tilePath": "http://raw.communitydragon.org/pbe/plugins/rcp-be-lol-game-data/global/default/v1/champion-tiles/429/429001.jpg",
      "loadScreenPath": "https://raw.communitydragon.org/pbe/plugins/rcp-be-lol-game-data/global/default/assets/characters/kalista/skins/skin01/kalistaloadscreen_1.jpg",
      "loadScreenVintagePath": null,
      "newEffects": true,
      "newAnimations": true,
      "newRecall": true,
      "newVoice": false,
      "newQuotes": false,
      "voiceActor": [
        "Misty Lee"
      ],
      "splashArtist": []
    },
    {
      "name": "Worlds 2015",
      "id": 429002,
      "isBase": false,
      "availability": "Legacy",
      "formatName": "Worlds 2015",
      "lootEligible": true,
      "cost": 975,
      "sale": 0,
      "distribution": null,
      "rarity": "NoRarity",
      "chromas": [
        {
          "name": "Golden",
          "id": 429004,
          "chromaPath": "http://raw.communitydragon.org/pbe/plugins/rcp-be-lol-game-data/global/default/v1/champion-chroma-images/429/429004.png",
          "colors": [
            "#FFEE59",
            "#FFEE59"
          ],
          "descriptions": [
            {
              "description": "This chroma was released as a Loot exclusive during a Worlds event.",
              "region": "riot"
            }
          ],
          "rarities": [
            {
              "rarity": 2,
              "region": "riot"
            }
          ]
        }
      ],
      "lore": "Celebrating Worlds 2015 in Europe.",
      "release": "2015-09-27",
      "set": [
        "World Championship"
      ],
      "splashPath": "http://raw.communitydragon.org/pbe/plugins/rcp-be-lol-game-data/global/default/v1/champion-splashes/429/429002.jpg",
      "uncenteredSplashPath": "http://raw.communitydragon.org/pbe/plugins/rcp-be-lol-game-data/global/default/v1/champion-splashes/uncentered/429/429002.jpg",
      "tilePath": "http://raw.communitydragon.org/pbe/plugins/rcp-be-lol-game-data/global/default/v1/champion-tiles/429/429002.jpg",
      "loadScreenPath": "https://raw.communitydragon.org/pbe/plugins/rcp-be-lol-game-data/global/default/assets/characters/kalista/skins/skin02/kalistaloadscreen_2.jpg",
      "loadScreenVintagePath": "https://raw.communitydragon.org/pbe/plugins/rcp-be-lol-game-data/global/default/assets/characters/kalista/skins/skin02/kalistaloadscreen_2_le.jpg",
      "newEffects": true,
      "newAnimations": true,
      "newRecall": true,
      "newVoice": false,
      "newQuotes": false,
      "voiceActor": [
        "Misty Lee"
      ],
      "splashArtist": [
        "Christian Fell"
      ]
    },
    {
      "name": "SKT T1",
      "id": 429003,
      "isBase": false,
      "availability": "Legacy",
      "formatName": "SKT T1",
      "lootEligible": true,
      "cost": 975,
      "sale": 0,
      "distribution": null,
      "rarity": "NoRarity",
      "chromas": [],
      "lore": "Honoring Bang's winning performance as Kalista during the 2015 World Championship.",
      "release": "2016-08-17",
      "set": [
        "World Champions: 2015"
      ],
      "splashPath": "http://raw.communitydragon.org/pbe/plugins/rcp-be-lol-game-data/global/default/v1/champion-splashes/429/429003.jpg",
      "uncenteredSplashPath": "http://raw.communitydragon.org/pbe/plugins/rcp-be-lol-game-data/global/default/v1/champion-splashes/uncentered/429/429003.jpg",
      "tilePath": "http://raw.communitydragon.org/pbe/plugins/rcp-be-lol-game-data/global/default/v1/champion-tiles/429/429003.jpg",
      "loadScreenPath": "https://raw.communitydragon.org/pbe/plugins/rcp-be-lol-game-data/global/default/assets/characters/kalista/skins/skin03/kalistaloadscreen_3.jpg",
      "loadScreenVintagePath": null,
      "newEffects": true,
      "newAnimations": true,
      "newRecall": true,
      "newVoice": false,
      "newQuotes": false,
      "voiceActor": [
        "Misty Lee"
      ],
      "splashArtist": [
        "Victor '3rdColossus' Maury"
      ]
    },
    {
      "name": "Marauder",
      "id": 429005,
      "isBase": false,
      "availability": "Available",
      "formatName": "Marauder",
      "lootEligible": true,
      "cost": 1350,
      "sale": 0,
      "distribution": null,
      "rarity": "Epic",
      "chromas": [
        {
          "name": "Amethyst",
          "id": 429011,
          "chromaPath": "http://raw.communitydragon.org/pbe/plugins/rcp-be-lol-game-data/global/default/v1/champion-chroma-images/429/429011.png",
          "colors": [
            "#9C68D7",
            "#9C68D7"
          ],
          "descriptions": [
            {
              "description": null,
              "region": null
            }
          ],
          "rarities": [
            {
              "rarity": null,
              "region": null
            }
          ]
        },
        {
          "name": "Citrine",
          "id": 429006,
          "chromaPath": "http://raw.communitydragon.org/pbe/plugins/rcp-be-lol-game-data/global/default/v1/champion-chroma-images/429/429006.png",
          "colors": [
            "#DF9117",
            "#DF9117"
          ],
          "descriptions": [
            {
              "description": null,
              "region": null
            }
          ],
          "rarities": [
            {
              "rarity": null,
              "region": null
            }
          ]
        },
        {
          "name": "Emerald",
          "id": 429013,
          "chromaPath": "http://raw.communitydragon.org/pbe/plugins/rcp-be-lol-game-data/global/default/v1/champion-chroma-images/429/429013.png",
          "colors": [
            "#2DA130",
            "#2DA130"
          ],
          "descriptions": [
            {
              "description": null,
              "region": null
            }
          ],
          "rarities": [
            {
              "rarity": null,
              "region": null
            }
          ]
        },
        {
          "name": "Obsidian",
          "id": 429008,
          "chromaPath": "http://raw.communitydragon.org/pbe/plugins/rcp-be-lol-game-data/global/default/v1/champion-chroma-images/429/429008.png",
          "colors": [
            "#27211C",
            "#27211C"
          ],
          "descriptions": [
            {
              "description": null,
              "region": null
            }
          ],
          "rarities": [
            {
              "rarity": null,
              "region": null
            }
          ]
        },
        {
          "name": "Rose Quartz",
          "id": 429010,
          "chromaPath": "http://raw.communitydragon.org/pbe/plugins/rcp-be-lol-game-data/global/default/v1/champion-chroma-images/429/429010.png",
          "colors": [
            "#E58BA5",
            "#E58BA5"
          ],
          "descriptions": [
            {
              "description": null,
              "region": null
            }
          ],
          "rarities": [
            {
              "rarity": 1,
              "region": "TENCENT"
            }
          ]
        },
        {
          "name": "Ruby",
          "id": 429009,
          "chromaPath": "http://raw.communitydragon.org/pbe/plugins/rcp-be-lol-game-data/global/default/v1/champion-chroma-images/429/429009.png",
          "colors": [
            "#D33528",
            "#D33528"
          ],
          "descriptions": [
            {
              "description": "This chroma was released as a bundle exclusive in 2021.",
              "region": "riot"
            }
          ],
          "rarities": [
            {
              "rarity": 1,
              "region": "riot"
            }
          ]
        },
        {
          "name": "Sapphire",
          "id": 429007,
          "chromaPath": "http://raw.communitydragon.org/pbe/plugins/rcp-be-lol-game-data/global/default/v1/champion-chroma-images/429/429007.png",
          "colors": [
            "#2756CE",
            "#2756CE"
          ],
          "descriptions": [
            {
              "description": null,
              "region": null
            }
          ],
          "rarities": [
            {
              "rarity": null,
              "region": null
            }
          ]
        },
        {
          "name": "Turquoise",
          "id": 429012,
          "chromaPath": "http://raw.communitydragon.org/pbe/plugins/rcp-be-lol-game-data/global/default/v1/champion-chroma-images/429/429012.png",
          "colors": [
            "#73BFBE",
            "#73BFBE"
          ],
          "descriptions": [
            {
              "description": null,
              "region": null
            }
          ],
          "rarities": [
            {
              "rarity": null,
              "region": null
            }
          ]
        }
      ],
      "lore": "The Magelords… furious, brutal, and glorious in their conquest—a sect of warriors long lost to the sands of time. Until now. Resurrected by the current Marauder leaders, Kalista's desire for vengeance has only festered over the millenia. Now she returns, more powerful than ever, to eradicate the Wardens and everything they've built.",
      "release": "2021-01-07",
      "set": [
        "Marauder"
      ],
      "splashPath": "http://raw.communitydragon.org/pbe/plugins/rcp-be-lol-game-data/global/default/v1/champion-splashes/429/429005.jpg",
      "uncenteredSplashPath": "http://raw.communitydragon.org/pbe/plugins/rcp-be-lol-game-data/global/default/v1/champion-splashes/uncentered/429/429005.jpg",
      "tilePath": "http://raw.communitydragon.org/pbe/plugins/rcp-be-lol-game-data/global/default/v1/champion-tiles/429/429005.jpg",
      "loadScreenPath": "https://raw.communitydragon.org/pbe/plugins/rcp-be-lol-game-data/global/default/assets/characters/kalista/skins/skin05/kalistaloadscreen_5.jpg",
      "loadScreenVintagePath": null,
      "newEffects": true,
      "newAnimations": true,
      "newRecall": true,
      "newVoice": false,
      "newQuotes": false,
      "voiceActor": [
        "Misty Lee"
      ],
      "splashArtist": [
        "David Villegas",
        "West Studio"
      ]
    },
    {
      "name": "Faerie Court",
      "id": 429014,
      "isBase": false,
      "availability": "Available",
      "formatName": "Faerie Court",
      "lootEligible": true,
      "cost": 1350,
      "sale": 0,
      "distribution": null,
      "rarity": "Epic",
      "chromas": [
        {
          "name": "Amethyst",
          "id": 429019,
          "chromaPath": "http://raw.communitydragon.org/pbe/plugins/rcp-be-lol-game-data/global/default/v1/champion-chroma-images/429/429019.png",
          "colors": [
            "#9C68D7",
            "#9C68D7"
          ],
          "descriptions": [
            {
              "description": null,
              "region": null
            }
          ],
          "rarities": [
            {
              "rarity": null,
              "region": null
            }
          ]
        },
        {
          "name": "Catseye",
          "id": 429016,
          "chromaPath": "http://raw.communitydragon.org/pbe/plugins/rcp-be-lol-game-data/global/default/v1/champion-chroma-images/429/429016.png",
          "colors": [
            "#FFEE59",
            "#FFEE59"
          ],
          "descriptions": [
            {
              "description": null,
              "region": null
            }
          ],
          "rarities": [
            {
              "rarity": null,
              "region": null
            }
          ]
        },
        {
          "name": "Emerald",
          "id": 429018,
          "chromaPath": "http://raw.communitydragon.org/pbe/plugins/rcp-be-lol-game-data/global/default/v1/champion-chroma-images/429/429018.png",
          "colors": [
            "#2DA130",
            "#2DA130"
          ],
          "descriptions": [
            {
              "description": null,
              "region": null
            }
          ],
          "rarities": [
            {
              "rarity": null,
              "region": null
            }
          ]
        },
        {
          "name": "Pearl",
          "id": 429022,
          "chromaPath": "http://raw.communitydragon.org/pbe/plugins/rcp-be-lol-game-data/global/default/v1/champion-chroma-images/429/429022.png",
          "colors": [
            "#ECF9F8",
            "#ECF9F8"
          ],
          "descriptions": [
            {
              "description": null,
              "region": null
            }
          ],
          "rarities": [
            {
              "rarity": null,
              "region": null
            }
          ]
        },
        {
          "name": "Rose Quartz",
          "id": 429015,
          "chromaPath": "http://raw.communitydragon.org/pbe/plugins/rcp-be-lol-game-data/global/default/v1/champion-chroma-images/429/429015.png",
          "colors": [
            "#E58BA5",
            "#E58BA5"
          ],
          "descriptions": [
            {
              "description": null,
              "region": null
            }
          ],
          "rarities": [
            {
              "rarity": 1,
              "region": "TENCENT"
            }
          ]
        },
        {
          "name": "Ruby",
          "id": 429021,
          "chromaPath": "http://raw.communitydragon.org/pbe/plugins/rcp-be-lol-game-data/global/default/v1/champion-chroma-images/429/429021.png",
          "colors": [
            "#D33528",
            "#D33528"
          ],
          "descriptions": [
            {
              "description": "This chroma was released as a bundle exclusive in 2023.",
              "region": "riot"
            }
          ],
          "rarities": [
            {
              "rarity": 1,
              "region": "riot"
            }
          ]
        },
        {
          "name": "Sapphire",
          "id": 429017,
          "chromaPath": "http://raw.communitydragon.org/pbe/plugins/rcp-be-lol-game-data/global/default/v1/champion-chroma-images/429/429017.png",
          "colors": [
            "#2756CE",
            "#2756CE"
          ],
          "descriptions": [
            {
              "description": null,
              "region": null
            }
          ],
          "rarities": [
            {
              "rarity": null,
              "region": null
            }
          ]
        },
        {
          "name": "Turquoise",
          "id": 429020,
          "chromaPath": "http://raw.communitydragon.org/pbe/plugins/rcp-be-lol-game-data/global/default/v1/champion-chroma-images/429/429020.png",
          "colors": [
            "#73BFBE",
            "#73BFBE"
          ],
          "descriptions": [
            {
              "description": null,
              "region": null
            }
          ],
          "rarities": [
            {
              "rarity": null,
              "region": null
            }
          ]
        },
        {
          "name": "Winsome",
          "id": 429023,
          "chromaPath": "http://raw.communitydragon.org/pbe/plugins/rcp-be-lol-game-data/global/default/v1/champion-chroma-images/429/429023.png",
          "colors": [
            "#866EFF",
            "#8AE1E8"
          ],
          "descriptions": [
            {
              "description": "This chroma was released as a Loot exclusive in the 2023 Faerie Court event.",
              "region": "riot"
            }
          ],
          "rarities": [
            {
              "rarity": 1,
              "region": "riot"
            }
          ]
        }
      ],
      "lore": "As captain of Her Majesty's royal guard, Kalista is dedicated to keeping her queen safe above all else. Though some grumble that Kalista was only elevated to her station because she is Karma's dearest friend, she has proven time and time again that her title is well earned. Anyone who thinks otherwise is welcome to duel her and learn firsthand.",
      "release": "2023-03-23",
      "set": [
        "Faerie Court"
      ],
      "splashPath": "http://raw.communitydragon.org/pbe/plugins/rcp-be-lol-game-data/global/default/v1/champion-splashes/429/429014.jpg",
      "uncenteredSplashPath": "http://raw.communitydragon.org/pbe/plugins/rcp-be-lol-game-data/global/default/v1/champion-splashes/uncentered/429/429014.jpg",
      "tilePath": "http://raw.communitydragon.org/pbe/plugins/rcp-be-lol-game-data/global/default/v1/champion-tiles/429/429014.jpg",
      "loadScreenPath": "https://raw.communitydragon.org/pbe/plugins/rcp-be-lol-game-data/global/default/assets/characters/kalista/skins/skin14/kalistaloadscreen_14.jpg",
      "loadScreenVintagePath": "https://raw.communitydragon.org/pbe/plugins/rcp-be-lol-game-data/global/default/assets/characters/kalista/skins/skin14/kalistaloadscreen_14_le.jpg",
      "newEffects": true,
      "newAnimations": true,
      "newRecall": true,
      "newVoice": false,
      "newQuotes": false,
      "voiceActor": [
        "Misty Lee"
      ],
      "splashArtist": [
        "Francis Tneh",
        "West Studio"
      ]
    }
  ]
}