{
  "id": 16,
  "key": "Soraka",
  "name": "Soraka",
  "title": "the Starchild",
  "fullName": "",
  "icon": "http://ddragon.leagueoflegends.com/cdn/14.7.1/img/champion/Soraka.png",
  "resource": "MANA",
  "attackType": "RANGED",
  "adaptiveType": "MAGIC_DAMAGE",
  "stats": {
    "health": {
      "flat": 605,
      "percent": 0,
      "perLevel": 88,
      "percentPerLevel": 0
    },
    "healthRegen": {
      "flat": 2.5,
      "percent": 0,
      "perLevel": 0.5,
      "percentPerLevel": 0
    },
    "mana": {
      "flat": 425,
      "percent": 0,
      "perLevel": 40,
      "percentPerLevel": 0
    },
    "manaRegen": {
      "flat": 11.5,
      "percent": 0,
      "perLevel": 0.4,
      "percentPerLevel": 0
    },
    "armor": {
      "flat": 32,
      "percent": 0,
      "perLevel": 5,
      "percentPerLevel": 0
    },
    "magicResistance": {
      "flat": 30,
      "percent": 0,
      "perLevel": 1.3,
      "percentPerLevel": 0
    },
    "attackDamage": {
      "flat": 50,
      "percent": 0,
      "perLevel": 3,
      "percentPerLevel": 0
    },
    "movespeed": {
      "flat": 325,
      "percent": 0,
      "perLevel": 0,
      "percentPerLevel": 0
    },
    "acquisitionRadius": {
      "flat": 600,
      "percent": 0,
      "perLevel": 0,
      "percentPerLevel": 0
    },
    "selectionRadius": {
      "flat": 110,
      "percent": 0,
      "perLevel": 0,
      "percentPerLevel": 0
    },
    "pathingRadius": {
      "flat": 44.2000007629394,
      "percent": 0,
      "perLevel": 0,
      "percentPerLevel": 0
    },
    "gameplayRadius": {
      "flat": 65,
      "percent": 0,
      "perLevel": 0,
      "percentPerLevel": 0
    },
    "criticalStrikeDamage": {
      "flat": 175,
      "percent": 0,
      "perLevel": 0,
      "percentPerLevel": 0
    },
    "criticalStrikeDamageModifier": {
      "flat": 1,
      "percent": 0,
      "perLevel": 0,
      "percentPerLevel": 0
    },
    "attackSpeed": {
      "flat": 0.625,
      "percent": 0,
      "perLevel": 2.14,
      "percentPerLevel": 0
    },
    "attackSpeedRatio": {
      "flat": 0.625,
      "percent": 0,
      "perLevel": 0,
      "percentPerLevel": 0
    },
    "attackCastTime": {
      "flat": 0.3,
      "percent": 0,
      "perLevel": 0,
      "percentPerLevel": 0
    },
    "attackTotalTime": {
      "flat": 1.6,
      "percent": 0,
      "perLevel": 0,
      "percentPerLevel": 0
    },
    "attackDelayOffset": {
      "flat": -0.112999998033046,
      "percent": 0,
      "perLevel": 0,
      "percentPerLevel": 0
    },
    "attackRange": {
      "flat": 550,
      "percent": 0,
      "perLevel": 0,
      "percentPerLevel": 0
    },
    "aramDamageTaken": {
      "flat": 1,
      "percent": 0,
      "perLevel": 0,
      "percentPerLevel": 0
    },
    "aramDamageDealt": {
      "flat": 1,
      "percent": 0,
      "perLevel": 0,
      "percentPerLevel": 0
    },
    "aramHealing": {
      "flat": 1,
      "percent": 0,
      "perLevel": 0,
      "percentPerLevel": 0
    },
    "aramShielding": {
      "flat": 1,
      "percent": 0,
      "perLevel": 0,
      "percentPerLevel": 0
    },
    "urfDamageTaken": {
      "flat": 0.92,
      "percent": 0,
      "perLevel": 0,
      "percentPerLevel": 0
    },
    "urfDamageDealt": {
      "flat": 1.05,
      "percent": 0,
      "perLevel": 0,
      "percentPerLevel": 0
    },
    "urfHealing": {
      "flat": 1,
      "percent": 0,
      "perLevel": 0,
      "percentPerLevel": 0
    },
    "urfShielding": {
      "flat": 1,
      "percent": 0,
      "perLevel": 0,
      "percentPerLevel": 0
    }
  },
  "roles": [
    "ENCHANTER",
    "MAGE",
    "SUPPORT"
  ],
  "attributeRatings": {
    "damage": 1,
    "toughness": 1,
    "control": 2,
    "mobility": 1,
    "utility": 3,
    "abilityReliance": 100,
    "difficulty": 1
  },
  "abilities": {
    "P": [
      {
        "name": "Salvation",
        "icon": "https://cdn.communitydragon.org/latest/champion/Soraka/ability-icon/p",
        "effects": [
          {
            "description": "Innate: Soraka gains 90% bonus movement speed while facing nearby allied champions that are below 40% of their maximum health.",
            "leveling": []
          }
        ],
        "cost": null,
        "cooldown": null,
        "targeting": "Passive",
        "affects": "Self",
        "spellshieldable": null,
        "resource": null,
        "damageType": null,
        "spellEffects": null,
        "projectile": null,
        "onHitEffects": null,
        "occurrence": null,
        "notes": "Soraka will see an arrow indicating the direction in which she can gain the bonus movement speed.",
        "blurb": "Innate:  Soraka gains tremendous  bonus movement speed while facing nearby allied  champions that are at low health.",
        "missileSpeed": null,
        "rechargeRate": null,
        "collisionRadius": null,
        "tetherRadius": null,
        "onTargetCdStatic": null,
        "innerRadius": null,
        "speed": null,
        "width": null,
        "angle": null,
        "castTime": null,
        "effectRadius": "2500",
        "targetRange": null
      }
    ],
    "Q": [
      {
        "name": "Starcall",
        "icon": "https://cdn.communitydragon.org/latest/champion/Soraka/ability-icon/q",
        "effects": [
          {
            "description": "Active: Soraka calls down a star upon the target location that grants sight of the area before landing after 0.25 − 1 (based on target range) seconds, dealing magic damage to enemies hit and slowing them by 30% for 1.5 seconds.",
            "leveling": [
              {
                "attribute": "Magic Damage",
                "modifiers": [
                  {
                    "values": [
                      85,
                      120,
                      155,
                      190,
                      225
                    ],
                    "units": [
                      "",
                      "",
                      "",
                      "",
                      ""
                    ]
                  },
                  {
                    "values": [
                      35,
                      35,
                      35,
                      35,
                      35
                    ],
                    "units": [
                      "% AP",
                      "% AP",
                      "% AP",
                      "% AP",
                      "% AP"
                    ]
                  }
                ]
              }
            ]
          },
          {
            "description": "If this hits at least one enemy champion, the star dust returns to Soraka to grant her Rejuvenation for 2.5 seconds. While Soraka has Rejuvenation, Astral Infusion will also grant the effects of Rejuvenation to the target ally for the same duration.",
            "leveling": []
          },
          {
            "description": "Rejuvenation: The target heals every 0.5 seconds and gains bonus movement speed that decays over the duration.",
            "leveling": [
              {
                "attribute": "Total Heal",
                "modifiers": [
                  {
                    "values": [
                      60,
                      75,
                      90,
                      105,
                      120
                    ],
                    "units": [
                      "",
                      "",
                      "",
                      "",
                      ""
                    ]
                  },
                  {
                    "values": [
                      30,
                      30,
                      30,
                      30,
                      30
                    ],
                    "units": [
                      "% AP",
                      "% AP",
                      "% AP",
                      "% AP",
                      "% AP"
                    ]
                  }
                ]
              },
              {
                "attribute": "Heal per Tick",
                "modifiers": [
                  {
                    "values": [
                      12,
                      15,
                      18,
                      21,
                      24
                    ],
                    "units": [
                      "",
                      "",
                      "",
                      "",
                      ""
                    ]
                  },
                  {
                    "values": [
                      6,
                      6,
                      6,
                      6,
                      6
                    ],
                    "units": [
                      "% AP",
                      "% AP",
                      "% AP",
                      "% AP",
                      "% AP"
                    ]
                  }
                ]
              },
              {
                "attribute": "Bonus Movement Speed",
                "modifiers": [
                  {
                    "values": [
                      20,
                      22.5,
                      25,
                      27.5,
                      30
                    ],
                    "units": [
                      "%",
                      "%",
                      "%",
                      "%",
                      "%"
                    ]
                  }
                ]
              }
            ]
          }
        ],
        "cost": {
          "modifiers": [
            {
              "values": [
                45,
                50,
                55,
                60,
                65
              ],
              "units": [
                "",
                "",
                "",
                "",
                ""
              ]
            }
          ]
        },
        "cooldown": {
          "modifiers": [
            {
              "values": [
                8,
                7,
                6,
                5,
                4
              ],
              "units": [
                "",
                "",
                "",
                "",
                ""
              ]
            }
          ],
          "affectedByCdr": true
        },
        "targeting": "Location",
        "affects": "Self, Enemies",
        "spellshieldable": "True",
        "resource": "MANA",
        "damageType": "MAGIC_DAMAGE",
        "spellEffects": "spellaoe",
        "projectile": "TRUE",
        "onHitEffects": null,
        "occurrence": null,
        "notes": "Starcall counts as hitting even if it gets blocked by  spell shield, granting Rejuvenation.\n Yasuo's  Wind Wall and  Braum's  Unbreakable can block the Rejuvenation projectile.\nRejuvenation heals over 12 ticks, with the first 4 each healing for about 15% of the heal, the next 4 ticks for about 5.5% each, and the last 4 for about 4.5% each.\nRejuvenation won't be granted to Soraka and she won't be able to make use of the health cost reduction on  Astral Infusion until the projectile gets to her, but she is able to Rejuvenate allies as soon as the target is hit.",
        "blurb": "Active:  Soraka calls down a star upon the target location that deals magic damage and briefly  slows enemies hit. If this hits at least one enemy  champion, the star dust returns to Soraka to grant her Rejuvenation for a short time.",
        "missileSpeed": null,
        "rechargeRate": null,
        "collisionRadius": null,
        "tetherRadius": null,
        "onTargetCdStatic": null,
        "innerRadius": null,
        "speed": null,
        "width": null,
        "angle": null,
        "castTime": "0.25",
        "effectRadius": "265",
        "targetRange": "800"
      }
    ],
    "W": [
      {
        "name": "Astral Infusion",
        "icon": "https://cdn.communitydragon.org/latest/champion/Soraka/ability-icon/w",
        "effects": [
          {
            "description": "Active: Soraka heals the target allied champion.",
            "leveling": [
              {
                "attribute": "Heal",
                "modifiers": [
                  {
                    "values": [
                      90,
                      110,
                      130,
                      150,
                      170
                    ],
                    "units": [
                      "",
                      "",
                      "",
                      "",
                      ""
                    ]
                  },
                  {
                    "values": [
                      50,
                      50,
                      50,
                      50,
                      50
                    ],
                    "units": [
                      "% AP",
                      "% AP",
                      "% AP",
                      "% AP",
                      "% AP"
                    ]
                  }
                ]
              }
            ]
          },
          {
            "description": "If cast while under Rejuvenation, the health cost will be reduced by a percentage.",
            "leveling": [
              {
                "attribute": "Health Cost Reduction",
                "modifiers": [
                  {
                    "values": [
                      80,
                      85,
                      90,
                      95,
                      100
                    ],
                    "units": [
                      "%",
                      "%",
                      "%",
                      "%",
                      "%"
                    ]
                  }
                ]
              },
              {
                "attribute": "Reduced Health Cost",
                "modifiers": [
                  {
                    "values": [
                      2,
                      1.5,
                      1,
                      0.5,
                      0
                    ],
                    "units": [
                      "% of maximum health",
                      "% of maximum health",
                      "% of maximum health",
                      "% of maximum health",
                      "% of maximum health"
                    ]
                  }
                ]
              }
            ]
          },
          {
            "description": "Astral Infusion cannot be cast if Soraka is below 5% of her maximum health.",
            "leveling": []
          }
        ],
        "cost": {
          "modifiers": [
            {
              "values": [
                10,
                10,
                10,
                10,
                10
              ],
              "units": [
                "%",
                "%",
                "%",
                "%",
                "%"
              ]
            }
          ]
        },
        "cooldown": {
          "modifiers": [
            {
              "values": [
                6,
                5,
                4,
                3,
                2
              ],
              "units": [
                "",
                "",
                "",
                "",
                ""
              ]
            }
          ],
          "affectedByCdr": true
        },
        "targeting": "Unit",
        "affects": "Allies / Self",
        "spellshieldable": null,
        "resource": "OTHER",
        "damageType": null,
        "spellEffects": "Heal",
        "projectile": "FALSE",
        "onHitEffects": null,
        "occurrence": null,
        "notes": "Astral Infusion can also be targeted on allied  decoys.\nAstral Infusion can be cast even if Soraka doesn't have the sufficient amount of health to pay for the health cost while above  5% of her maximum health.\nAs with all abilities with health costs, Astral Infusion will not reduce Soraka's health below 1.\n Spirit Visage will only increase the health donated to allies if the target ally possesses it, although owning it will boost the heal that Soraka receives from  Starcall and  Wish.\nAstral Infusion's effects occur before the cast time.",
        "blurb": "Active:  Soraka consumes a portion of her maximum health to  heal the target allied champion.",
        "missileSpeed": null,
        "rechargeRate": null,
        "collisionRadius": null,
        "tetherRadius": null,
        "onTargetCdStatic": null,
        "innerRadius": null,
        "speed": null,
        "width": null,
        "angle": null,
        "castTime": "0.25",
        "effectRadius": null,
        "targetRange": "550"
      }
    ],
    "E": [
      {
        "name": "Equinox",
        "icon": "https://cdn.communitydragon.org/latest/champion/Soraka/ability-icon/e",
        "effects": [
          {
            "description": "Active: Soraka creates a celestial zone at the target location that deals magic damage to enemy champions within at the time of cast. The zone then persists for 1.5 seconds and silences enemies within.",
            "leveling": [
              {
                "attribute": "Magic Damage",
                "modifiers": [
                  {
                    "values": [
                      70,
                      95,
                      120,
                      145,
                      170
                    ],
                    "units": [
                      "",
                      "",
                      "",
                      "",
                      ""
                    ]
                  },
                  {
                    "values": [
                      40,
                      40,
                      40,
                      40,
                      40
                    ],
                    "units": [
                      "% AP",
                      "% AP",
                      "% AP",
                      "% AP",
                      "% AP"
                    ]
                  }
                ]
              }
            ]
          },
          {
            "description": "Afterwards, the zone erupts to deal the same damage to enemy champions within and root them for a duration.",
            "leveling": [
              {
                "attribute": "Total Magic Damage",
                "modifiers": [
                  {
                    "values": [
                      140,
                      190,
                      240,
                      290,
                      340
                    ],
                    "units": [
                      "",
                      "",
                      "",
                      "",
                      ""
                    ]
                  },
                  {
                    "values": [
                      80,
                      80,
                      80,
                      80,
                      80
                    ],
                    "units": [
                      "% AP",
                      "% AP",
                      "% AP",
                      "% AP",
                      "% AP"
                    ]
                  }
                ]
              },
              {
                "attribute": "Root Duration",
                "modifiers": [
                  {
                    "values": [
                      1,
                      1.25,
                      1.5,
                      1.75,
                      2
                    ],
                    "units": [
                      "",
                      "",
                      "",
                      "",
                      ""
                    ]
                  }
                ]
              }
            ]
          }
        ],
        "cost": {
          "modifiers": [
            {
              "values": [
                70,
                75,
                80,
                85,
                90
              ],
              "units": [
                "",
                "",
                "",
                "",
                ""
              ]
            }
          ]
        },
        "cooldown": {
          "modifiers": [
            {
              "values": [
                20,
                19,
                18,
                17,
                16
              ],
              "units": [
                "",
                "",
                "",
                "",
                ""
              ]
            }
          ],
          "affectedByCdr": true
        },
        "targeting": "Location",
        "affects": "Enemies",
        "spellshieldable": "special",
        "resource": "MANA",
        "damageType": "MAGIC_DAMAGE",
        "spellEffects": "spellaoe",
        "projectile": null,
        "onHitEffects": null,
        "occurrence": null,
        "notes": "Equinox's  silence is marked as non-dispellable, so it is not removed by most  cleanses. It is however allowed to be removed by cleanses that also grant immunity to it, such as  Olaf's  Ragnarok.\n Spell shield will not block the  silence.",
        "blurb": "Active:  Soraka creates a celestial zone at the target location that deals magic damage to enemy champions within upon casting. The zone then persists for a brief moment and  siliences enemies within.",
        "missileSpeed": null,
        "rechargeRate": null,
        "collisionRadius": null,
        "tetherRadius": null,
        "onTargetCdStatic": null,
        "innerRadius": null,
        "speed": null,
        "width": null,
        "angle": null,
        "castTime": "0.25",
        "effectRadius": "260",
        "targetRange": "925"
      }
    ],
    "R": [
      {
        "name": "Wish",
        "icon": "https://cdn.communitydragon.org/latest/champion/Soraka/ability-icon/r",
        "effects": [
          {
            "description": "Active: Soraka calls upon the stars, healing herself and all allied champions, increased by 50% on targets below 40% of their maximum health.",
            "leveling": [
              {
                "attribute": "Heal",
                "modifiers": [
                  {
                    "values": [
                      150,
                      250,
                      350
                    ],
                    "units": [
                      "",
                      "",
                      ""
                    ]
                  },
                  {
                    "values": [
                      50,
                      50,
                      50
                    ],
                    "units": [
                      "% AP",
                      "% AP",
                      "% AP"
                    ]
                  }
                ]
              },
              {
                "attribute": "Increased Heal",
                "modifiers": [
                  {
                    "values": [
                      225,
                      375,
                      525
                    ],
                    "units": [
                      "",
                      "",
                      ""
                    ]
                  },
                  {
                    "values": [
                      75,
                      75,
                      75
                    ],
                    "units": [
                      "% AP",
                      "% AP",
                      "% AP"
                    ]
                  }
                ]
              }
            ]
          }
        ],
        "cost": {
          "modifiers": [
            {
              "values": [
                100,
                100,
                100
              ],
              "units": [
                "",
                "",
                ""
              ]
            }
          ]
        },
        "cooldown": {
          "modifiers": [
            {
              "values": [
                150,
                135,
                120
              ],
              "units": [
                "",
                "",
                ""
              ]
            }
          ],
          "affectedByCdr": true
        },
        "targeting": "Auto",
        "affects": "Allies",
        "spellshieldable": null,
        "resource": "MANA",
        "damageType": null,
        "spellEffects": "Heal",
        "projectile": null,
        "onHitEffects": null,
        "occurrence": null,
        "notes": "Due to several character stats needing to be recalculated each time a character spawns, casting Wish immediately upon respawning will cause its cooldown to be unaffected by ability haste, and the healing will not be increased by Soraka's ability power. (bug)\n Untargetability does not invalidate the targeting of the heal.\nWish will not credit Soraka for assisting in a champion kill if the target ally is at full health.\nWish will apply heal effects (such as  Summon Aery) prioritizing targets based on the Spawn ID, which is the order in which units were added to an ongoing game. For  champions, this is the order they appear in from left to right in the loading screen.\nWish's effects occur before the cast time.",
        "blurb": "Active:  Soraka calls upon the stars,  healing herself and her allies. The healing is increased on targets at low health.",
        "missileSpeed": null,
        "rechargeRate": null,
        "collisionRadius": null,
        "tetherRadius": null,
        "onTargetCdStatic": null,
        "innerRadius": null,
        "speed": null,
        "width": null,
        "angle": null,
        "castTime": "0.25",
        "effectRadius": "Global",
        "targetRange": null
      }
    ]
  },
  "releaseDate": "2009-02-21",
  "releasePatch": "Alpha Week 2",
  "patchLastChanged": "14.4",
  "price": {
    "blueEssence": 450,
    "rp": 260,
    "saleRp": 0
  },
  "lore": "A wanderer from the celestial dimensions beyond Mount Targon, Soraka gave up her immortality to protect the mortal races from their own more violent instincts. She endeavors to spread the virtues of compassion and mercy to everyone she meets—even healing those who would wish harm upon her. And, for all Soraka has seen of this world's struggles, she still believes the people of Runeterra have yet to reach their full potential.",
  "faction": "mount-targon",
  "skins": [
    {
      "name": "Original",
      "id": 16000,
      "isBase": true,
      "availability": "Available",
      "formatName": "Original",
      "lootEligible": true,
      "cost": 260,
      "sale": 0,
      "distribution": null,
      "rarity": "NoRarity",
      "chromas": [],
      "lore": "A wanderer from the celestial dimensions beyond Mount Targon, Soraka gave up her immortality to protect the mortal races from their own more violent instincts. She endeavors to spread the virtues of compassion and mercy to everyone she meets—even healing those who would wish harm upon her. And, for all Soraka has seen of this world's struggles, she still believes the people of Runeterra have yet to reach their full potential.",
      "release": "2009-02-21",
      "set": [],
      "splashPath": "http://raw.communitydragon.org/pbe/plugins/rcp-be-lol-game-data/global/default/v1/champion-splashes/16/16000.jpg",
      "uncenteredSplashPath": "http://raw.communitydragon.org/pbe/plugins/rcp-be-lol-game-data/global/default/v1/champion-splashes/uncentered/16/16000.jpg",
      "tilePath": "http://raw.communitydragon.org/pbe/plugins/rcp-be-lol-game-data/global/default/v1/champion-tiles/16/16000.jpg",
      "loadScreenPath": "https://raw.communitydragon.org/pbe/plugins/rcp-be-lol-game-data/global/default/assets/characters/soraka/skins/base/sorakaloadscreen.jpg",
      "loadScreenVintagePath": null,
      "newEffects": false,
      "newAnimations": false,
      "newRecall": false,
      "newVoice": false,
      "newQuotes": false,
      "voiceActor": [
        "Lisa Lindsley"
      ],
      "splashArtist": []
    },
    {
      "name": "Dryad",
      "id": 16001,
      "isBase": false,
      "availability": "Available",
      "formatName": "Dryad",
      "lootEligible": true,
      "cost": 520,
      "sale": 0,
      "distribution": null,
      "rarity": "NoRarity",
      "chromas": [],
      "lore": "Too many forget that the heart of the Elderwood was once gentle and kind. Within its confines rested fae, sylvans, and dryads—creatures from another age, who looked upon humanity with curious eyes. Now only a scattered few remain, and fewer still, like Soraka, who regard humans fondly.",
      "release": "2010-06-03",
      "set": [
        "Elderwood"
      ],
      "splashPath": "http://raw.communitydragon.org/pbe/plugins/rcp-be-lol-game-data/global/default/v1/champion-splashes/16/16001.jpg",
      "uncenteredSplashPath": "http://raw.communitydragon.org/pbe/plugins/rcp-be-lol-game-data/global/default/v1/champion-splashes/uncentered/16/16001.jpg",
      "tilePath": "http://raw.communitydragon.org/pbe/plugins/rcp-be-lol-game-data/global/default/v1/champion-tiles/16/16001.jpg",
      "loadScreenPath": "https://raw.communitydragon.org/pbe/plugins/rcp-be-lol-game-data/global/default/assets/characters/soraka/skins/skin01/sorakaloadscreen_1.jpg",
      "loadScreenVintagePath": null,
      "newEffects": false,
      "newAnimations": false,
      "newRecall": false,
      "newVoice": false,
      "newQuotes": false,
      "voiceActor": [
        "Lisa Lindsley"
      ],
      "splashArtist": []
    },
    {
      "name": "Divine",
      "id": 16002,
      "isBase": false,
      "availability": "Available",
      "formatName": "Divine",
      "lootEligible": true,
      "cost": 975,
      "sale": 0,
      "distribution": null,
      "rarity": "NoRarity",
      "chromas": [],
      "lore": null,
      "release": "2010-11-02",
      "set": [
        "Otherroads"
      ],
      "splashPath": "http://raw.communitydragon.org/pbe/plugins/rcp-be-lol-game-data/global/default/v1/champion-splashes/16/16002.jpg",
      "uncenteredSplashPath": "http://raw.communitydragon.org/pbe/plugins/rcp-be-lol-game-data/global/default/v1/champion-splashes/uncentered/16/16002.jpg",
      "tilePath": "http://raw.communitydragon.org/pbe/plugins/rcp-be-lol-game-data/global/default/v1/champion-tiles/16/16002.jpg",
      "loadScreenPath": "https://raw.communitydragon.org/pbe/plugins/rcp-be-lol-game-data/global/default/assets/characters/soraka/skins/skin02/sorakaloadscreen_2.jpg",
      "loadScreenVintagePath": null,
      "newEffects": false,
      "newAnimations": false,
      "newRecall": false,
      "newVoice": false,
      "newQuotes": false,
      "voiceActor": [
        "Lisa Lindsley"
      ],
      "splashArtist": []
    },
    {
      "name": "Celestine",
      "id": 16003,
      "isBase": false,
      "availability": "Available",
      "formatName": "Celestine",
      "lootEligible": true,
      "cost": 975,
      "sale": 0,
      "distribution": null,
      "rarity": "NoRarity",
      "chromas": [],
      "lore": null,
      "release": "2013-03-05",
      "set": [
        "Rift Quest"
      ],
      "splashPath": "http://raw.communitydragon.org/pbe/plugins/rcp-be-lol-game-data/global/default/v1/champion-splashes/16/16003.jpg",
      "uncenteredSplashPath": "http://raw.communitydragon.org/pbe/plugins/rcp-be-lol-game-data/global/default/v1/champion-splashes/uncentered/16/16003.jpg",
      "tilePath": "http://raw.communitydragon.org/pbe/plugins/rcp-be-lol-game-data/global/default/v1/champion-tiles/16/16003.jpg",
      "loadScreenPath": "https://raw.communitydragon.org/pbe/plugins/rcp-be-lol-game-data/global/default/assets/characters/soraka/skins/skin03/sorakaloadscreen_3.jpg",
      "loadScreenVintagePath": null,
      "newEffects": true,
      "newAnimations": true,
      "newRecall": false,
      "newVoice": false,
      "newQuotes": false,
      "voiceActor": [
        "Lisa Lindsley"
      ],
      "splashArtist": [
        "Bo Lu"
      ]
    },
    {
      "name": "Reaper",
      "id": 16004,
      "isBase": false,
      "availability": "Legacy",
      "formatName": "Reaper",
      "lootEligible": true,
      "cost": 1350,
      "sale": 0,
      "distribution": null,
      "rarity": "Epic",
      "chromas": [],
      "lore": "With his silver tongue, Twisted Fate tricked the lords of the living to offer their beloved starchild to Death in exchange for their own immortality. Little did they know, eternal life without their avatar of compassion and mercy would result only in eternal suffering…",
      "release": "2014-11-05",
      "set": [
        "Death Sworn"
      ],
      "splashPath": "http://raw.communitydragon.org/pbe/plugins/rcp-be-lol-game-data/global/default/v1/champion-splashes/16/16004.jpg",
      "uncenteredSplashPath": "http://raw.communitydragon.org/pbe/plugins/rcp-be-lol-game-data/global/default/v1/champion-splashes/uncentered/16/16004.jpg",
      "tilePath": "http://raw.communitydragon.org/pbe/plugins/rcp-be-lol-game-data/global/default/v1/champion-tiles/16/16004.jpg",
      "loadScreenPath": "https://raw.communitydragon.org/pbe/plugins/rcp-be-lol-game-data/global/default/assets/characters/soraka/skins/skin04/sorakaloadscreen_4.jpg",
      "loadScreenVintagePath": null,
      "newEffects": true,
      "newAnimations": true,
      "newRecall": true,
      "newVoice": false,
      "newQuotes": false,
      "voiceActor": [
        "Lisa Lindsley"
      ],
      "splashArtist": [
        "Sperasoft Studio"
      ]
    },
    {
      "name": "Order of the Banana",
      "id": 16005,
      "isBase": false,
      "availability": "Available",
      "formatName": "Order of the Banana",
      "lootEligible": true,
      "cost": 750,
      "sale": 0,
      "distribution": null,
      "rarity": "NoRarity",
      "chromas": [],
      "lore": "Origins of the Order of the Banana date back nearly a year, when the idea of throwing a banana as a weapon first occurred to Soraka. Her and her fellow banana-ites swore an oath to uphold the Order of the Banana, promising to fling the yellow produce at anyone who decided to worship a different fruit. Especially pomegranates.",
      "release": "2015-03-31",
      "set": [
        "High Society"
      ],
      "splashPath": "http://raw.communitydragon.org/pbe/plugins/rcp-be-lol-game-data/global/default/v1/champion-splashes/16/16005.jpg",
      "uncenteredSplashPath": "http://raw.communitydragon.org/pbe/plugins/rcp-be-lol-game-data/global/default/v1/champion-splashes/uncentered/16/16005.jpg",
      "tilePath": "http://raw.communitydragon.org/pbe/plugins/rcp-be-lol-game-data/global/default/v1/champion-tiles/16/16005.jpg",
      "loadScreenPath": "https://raw.communitydragon.org/pbe/plugins/rcp-be-lol-game-data/global/default/assets/characters/soraka/skins/skin05/sorakaloadscreen_5.jpg",
      "loadScreenVintagePath": null,
      "newEffects": false,
      "newAnimations": false,
      "newRecall": false,
      "newVoice": false,
      "newQuotes": false,
      "voiceActor": [
        "Lisa Lindsley"
      ],
      "splashArtist": []
    },
    {
      "name": "Program",
      "id": 16006,
      "isBase": false,
      "availability": "Available",
      "formatName": "Program",
      "lootEligible": true,
      "cost": 1350,
      "sale": 0,
      "distribution": null,
      "rarity": "Epic",
      "chromas": [],
      "lore": "Program Soraka was created as a support bot to protect humanity's fragile nature, offering technological salvation at the hands of a mechanical angel. Infiltrated by corrupt code, it is unclear if this mission of mercy remains her prime directive.",
      "release": "2016-04-06",
      "set": [
        "Program"
      ],
      "splashPath": "http://raw.communitydragon.org/pbe/plugins/rcp-be-lol-game-data/global/default/v1/champion-splashes/16/16006.jpg",
      "uncenteredSplashPath": "http://raw.communitydragon.org/pbe/plugins/rcp-be-lol-game-data/global/default/v1/champion-splashes/uncentered/16/16006.jpg",
      "tilePath": "http://raw.communitydragon.org/pbe/plugins/rcp-be-lol-game-data/global/default/v1/champion-tiles/16/16006.jpg",
      "loadScreenPath": "https://raw.communitydragon.org/pbe/plugins/rcp-be-lol-game-data/global/default/assets/characters/soraka/skins/skin06/sorakaloadscreen_6.jpg",
      "loadScreenVintagePath": null,
      "newEffects": true,
      "newAnimations": true,
      "newRecall": true,
      "newVoice": false,
      "newQuotes": false,
      "voiceActor": [
        "Lisa Lindsley"
      ],
      "splashArtist": [
        "Kelly Aleshire"
      ]
    },
    {
      "name": "Star Guardian",
      "id": 16007,
      "isBase": false,
      "availability": "Available",
      "formatName": "Star Guardian",
      "lootEligible": true,
      "cost": 1350,
      "sale": 0,
      "distribution": null,
      "rarity": "Epic",
      "chromas": [],
      "lore": "A gentle soul with a mysterious origin among the stars, Soraka protects her team from behind the frontlines. Despite her shy appearance, she carries immense healing power and an unprecedented command of the Starlight, more than any other Star Guardian her team has encountered.",
      "release": "2017-09-06",
      "set": [
        "Star Guardian Season 2"
      ],
      "splashPath": "http://raw.communitydragon.org/pbe/plugins/rcp-be-lol-game-data/global/default/v1/champion-splashes/16/16007.jpg",
      "uncenteredSplashPath": "http://raw.communitydragon.org/pbe/plugins/rcp-be-lol-game-data/global/default/v1/champion-splashes/uncentered/16/16007.jpg",
      "tilePath": "http://raw.communitydragon.org/pbe/plugins/rcp-be-lol-game-data/global/default/v1/champion-tiles/16/16007.jpg",
      "loadScreenPath": "https://raw.communitydragon.org/pbe/plugins/rcp-be-lol-game-data/global/default/assets/characters/soraka/skins/skin07/sorakaloadscreen_7.jpg",
      "loadScreenVintagePath": "https://raw.communitydragon.org/pbe/plugins/rcp-be-lol-game-data/global/default/assets/characters/soraka/skins/skin07/sorakaloadscreen_7_le.jpg",
      "newEffects": true,
      "newAnimations": true,
      "newRecall": true,
      "newVoice": false,
      "newQuotes": false,
      "voiceActor": [
        "Lisa Lindsley"
      ],
      "splashArtist": [
        "Esben Lash Rasmussen",
        "Alex 'alexplank' Flores",
        "Alvin Lee",
        "Pan Chengwei",
        "Jean 'Curing' Go"
      ]
    },
    {
      "name": "Pajama Guardian",
      "id": 16008,
      "isBase": false,
      "availability": "Available",
      "formatName": "Pajama Guardian",
      "lootEligible": true,
      "cost": 1350,
      "sale": 0,
      "distribution": null,
      "rarity": "Epic",
      "chromas": [],
      "lore": "The other girls (and Ezreal) seemed excited for the pillow fights, and staying up all night talking. Soraka was most excited for the cinnamon rolls she brought from Pantheon's Pastries. But nothing makes her happier than seeing her friends smiling and laughing.",
      "release": "2018-11-21",
      "set": [
        "Star Guardian Season 2"
      ],
      "splashPath": "http://raw.communitydragon.org/pbe/plugins/rcp-be-lol-game-data/global/default/v1/champion-splashes/16/16008.jpg",
      "uncenteredSplashPath": "http://raw.communitydragon.org/pbe/plugins/rcp-be-lol-game-data/global/default/v1/champion-splashes/uncentered/16/16008.jpg",
      "tilePath": "http://raw.communitydragon.org/pbe/plugins/rcp-be-lol-game-data/global/default/v1/champion-tiles/16/16008.jpg",
      "loadScreenPath": "https://raw.communitydragon.org/pbe/plugins/rcp-be-lol-game-data/global/default/assets/characters/soraka/skins/skin08/sorakaloadscreen_8.jpg",
      "loadScreenVintagePath": "https://raw.communitydragon.org/pbe/plugins/rcp-be-lol-game-data/global/default/assets/characters/soraka/skins/skin07/sorakaloadscreen_7_le.jpg",
      "newEffects": true,
      "newAnimations": true,
      "newRecall": true,
      "newVoice": false,
      "newQuotes": false,
      "voiceActor": [
        "Lisa Lindsley"
      ],
      "splashArtist": [
        "Sangsoo Jeong"
      ]
    },
    {
      "name": "Winter Wonder",
      "id": 16009,
      "isBase": false,
      "availability": "Legacy",
      "formatName": "Winter Wonder",
      "lootEligible": true,
      "cost": 1350,
      "sale": 0,
      "distribution": null,
      "rarity": "Epic",
      "chromas": [
        {
          "name": "Amethyst",
          "id": 16013,
          "chromaPath": "http://raw.communitydragon.org/pbe/plugins/rcp-be-lol-game-data/global/default/v1/champion-chroma-images/16/16013.png",
          "colors": [
            "#9C68D7",
            "#9C68D7"
          ],
          "descriptions": [
            {
              "description": null,
              "region": null
            }
          ],
          "rarities": [
            {
              "rarity": 1,
              "region": "riot"
            }
          ]
        },
        {
          "name": "Obsidian",
          "id": 16012,
          "chromaPath": "http://raw.communitydragon.org/pbe/plugins/rcp-be-lol-game-data/global/default/v1/champion-chroma-images/16/16012.png",
          "colors": [
            "#27211C",
            "#27211C"
          ],
          "descriptions": [
            {
              "description": null,
              "region": null
            }
          ],
          "rarities": [
            {
              "rarity": 1,
              "region": "riot"
            }
          ]
        },
        {
          "name": "Pearl",
          "id": 16011,
          "chromaPath": "http://raw.communitydragon.org/pbe/plugins/rcp-be-lol-game-data/global/default/v1/champion-chroma-images/16/16011.png",
          "colors": [
            "#ECF9F8",
            "#ECF9F8"
          ],
          "descriptions": [
            {
              "description": null,
              "region": null
            }
          ],
          "rarities": [
            {
              "rarity": 1,
              "region": "riot"
            }
          ]
        },
        {
          "name": "Rose Quartz",
          "id": 16014,
          "chromaPath": "http://raw.communitydragon.org/pbe/plugins/rcp-be-lol-game-data/global/default/v1/champion-chroma-images/16/16014.png",
          "colors": [
            "#E58BA5",
            "#E58BA5"
          ],
          "descriptions": [
            {
              "description": null,
              "region": null
            }
          ],
          "rarities": [
            {
              "rarity": 1,
              "region": "riot"
            }
          ]
        },
        {
          "name": "Ruby",
          "id": 16010,
          "chromaPath": "http://raw.communitydragon.org/pbe/plugins/rcp-be-lol-game-data/global/default/v1/champion-chroma-images/16/16010.png",
          "colors": [
            "#D33528",
            "#D33528"
          ],
          "descriptions": [
            {
              "description": "This chroma was released as a bundle exclusive during 2018.",
              "region": "riot"
            }
          ],
          "rarities": [
            {
              "rarity": 2,
              "region": "riot"
            }
          ]
        }
      ],
      "lore": "A kindly duchess within the court of the Poro King, Soraka's lands are filled with beautiful animals made of pristine, enchanted ice. These menageries stretch for miles, tended by her retainers.",
      "release": "2018-12-06",
      "set": [
        "Winter Wonder"
      ],
      "splashPath": "http://raw.communitydragon.org/pbe/plugins/rcp-be-lol-game-data/global/default/v1/champion-splashes/16/16009.jpg",
      "uncenteredSplashPath": "http://raw.communitydragon.org/pbe/plugins/rcp-be-lol-game-data/global/default/v1/champion-splashes/uncentered/16/16009.jpg",
      "tilePath": "http://raw.communitydragon.org/pbe/plugins/rcp-be-lol-game-data/global/default/v1/champion-tiles/16/16009.jpg",
      "loadScreenPath": "https://raw.communitydragon.org/pbe/plugins/rcp-be-lol-game-data/global/default/assets/characters/soraka/skins/skin09/sorakaloadscreen_9.jpg",
      "loadScreenVintagePath": "https://raw.communitydragon.org/pbe/plugins/rcp-be-lol-game-data/global/default/assets/characters/soraka/skins/skin09/sorakaloadscreen_9_le.jpg",
      "newEffects": true,
      "newAnimations": true,
      "newRecall": true,
      "newVoice": false,
      "newQuotes": false,
      "voiceActor": [
        "Lisa Lindsley"
      ],
      "splashArtist": [
        "Choe HeonHwa"
      ]
    },
    {
      "name": "Dawnbringer",
      "id": 16015,
      "isBase": false,
      "availability": "Available",
      "formatName": "Dawnbringer",
      "lootEligible": true,
      "cost": 1820,
      "sale": 0,
      "distribution": null,
      "rarity": "Legendary",
      "chromas": [],
      "lore": "A child of the gods born when chaos slew order, Soraka contains within her the powers of both Riven and Yasuo. To end the conflict of the gods, she has embraced the light to pierce the darkness, drawing on the powers of dawn to bring order to the chaotic world.",
      "release": "2019-12-12",
      "set": [
        "Nightbringer and Dawnbringer"
      ],
      "splashPath": "http://raw.communitydragon.org/pbe/plugins/rcp-be-lol-game-data/global/default/v1/champion-splashes/16/16015.jpg",
      "uncenteredSplashPath": "http://raw.communitydragon.org/pbe/plugins/rcp-be-lol-game-data/global/default/v1/champion-splashes/uncentered/16/16015.jpg",
      "tilePath": "http://raw.communitydragon.org/pbe/plugins/rcp-be-lol-game-data/global/default/v1/champion-tiles/16/16015.jpg",
      "loadScreenPath": "https://raw.communitydragon.org/pbe/plugins/rcp-be-lol-game-data/global/default/assets/characters/soraka/skins/skin15/sorakaloadscreen_15.jpg",
      "loadScreenVintagePath": "https://raw.communitydragon.org/pbe/plugins/rcp-be-lol-game-data/global/default/assets/characters/soraka/skins/skin15/sorakaloadscreen_15_le.jpg",
      "newEffects": true,
      "newAnimations": true,
      "newRecall": true,
      "newVoice": true,
      "newQuotes": false,
      "voiceActor": [
        "Lisa Lindsley"
      ],
      "splashArtist": [
        "Jeremy 'Jermu' Anninos"
      ]
    },
    {
      "name": "Nightbringer",
      "id": 16016,
      "isBase": false,
      "availability": "Available",
      "formatName": "Nightbringer",
      "lootEligible": true,
      "cost": 1820,
      "sale": 0,
      "distribution": null,
      "rarity": "Legendary",
      "chromas": [],
      "lore": "A child of the gods born when chaos slew order, Soraka contains within her the powers of both Riven and Yasuo. To end the conflict of the gods, she has embraced the darkness to soothe the blinding light, drawing on the powers of night to create chaos and change in a too-static world.",
      "release": "2019-12-12",
      "set": [
        "Nightbringer and Dawnbringer"
      ],
      "splashPath": "http://raw.communitydragon.org/pbe/plugins/rcp-be-lol-game-data/global/default/v1/champion-splashes/16/16016.jpg",
      "uncenteredSplashPath": "http://raw.communitydragon.org/pbe/plugins/rcp-be-lol-game-data/global/default/v1/champion-splashes/uncentered/16/16016.jpg",
      "tilePath": "http://raw.communitydragon.org/pbe/plugins/rcp-be-lol-game-data/global/default/v1/champion-tiles/16/16016.jpg",
      "loadScreenPath": "https://raw.communitydragon.org/pbe/plugins/rcp-be-lol-game-data/global/default/assets/characters/soraka/skins/skin16/sorakaloadscreen_16.jpg",
      "loadScreenVintagePath": "https://raw.communitydragon.org/pbe/plugins/rcp-be-lol-game-data/global/default/assets/characters/soraka/skins/skin16/sorakaloadscreen_16_le.jpg",
      "newEffects": true,
      "newAnimations": true,
      "newRecall": true,
      "newVoice": true,
      "newQuotes": false,
      "voiceActor": [
        "Lisa Lindsley"
      ],
      "splashArtist": [
        "Jeremy 'Jermu' Anninos"
      ]
    },
    {
      "name": "Prestige Star Guardian",
      "id": 16017,
      "isBase": false,
      "availability": "Rare",
      "formatName": "Prestige Star Guardian",
      "lootEligible": true,
      "cost": "Special",
      "sale": 0,
      "distribution": "150 Mythic Essence",
      "rarity": "Mythic",
      "chromas": [],
      "lore": "Leaving the planet behind with Xayah and the other Star Guardians, Soraka's full powers have been unlocked by her undying love for her friends—in the hopes that one day they will find their companion lost in the final battle with the Twilight Star, and be a family once again.",
      "release": "2020-11-24",
      "set": [
        "Star Guardian Season 2"
      ],
      "splashPath": "http://raw.communitydragon.org/pbe/plugins/rcp-be-lol-game-data/global/default/v1/champion-splashes/16/16017.jpg",
      "uncenteredSplashPath": "http://raw.communitydragon.org/pbe/plugins/rcp-be-lol-game-data/global/default/v1/champion-splashes/uncentered/16/16017.jpg",
      "tilePath": "http://raw.communitydragon.org/pbe/plugins/rcp-be-lol-game-data/global/default/v1/champion-tiles/16/16017.jpg",
      "loadScreenPath": "https://raw.communitydragon.org/pbe/plugins/rcp-be-lol-game-data/global/default/assets/characters/soraka/skins/skin17/sorakaloadscreen_17.jpg",
      "loadScreenVintagePath": "https://raw.communitydragon.org/pbe/plugins/rcp-be-lol-game-data/global/default/assets/characters/soraka/skins/skin17/sorakaloadscreen_17_le.jpg",
      "newEffects": true,
      "newAnimations": true,
      "newRecall": true,
      "newVoice": false,
      "newQuotes": false,
      "voiceActor": [
        "Lisa Lindsley"
      ],
      "splashArtist": [
        "Sanhua Chen",
        "Kudos Productions"
      ]
    },
    {
      "name": "Cafe Cuties",
      "id": 16018,
      "isBase": false,
      "availability": "Available",
      "formatName": "Cafe Cuties",
      "lootEligible": true,
      "cost": 1350,
      "sale": 0,
      "distribution": null,
      "rarity": "Epic",
      "chromas": [
        {
          "name": "Catseye",
          "id": 16020,
          "chromaPath": "http://raw.communitydragon.org/pbe/plugins/rcp-be-lol-game-data/global/default/v1/champion-chroma-images/16/16020.png",
          "colors": [
            "#FFEE59",
            "#FFEE59"
          ],
          "descriptions": [
            {
              "description": null,
              "region": null
            }
          ],
          "rarities": [
            {
              "rarity": null,
              "region": null
            }
          ]
        },
        {
          "name": "Obsidian",
          "id": 16024,
          "chromaPath": "http://raw.communitydragon.org/pbe/plugins/rcp-be-lol-game-data/global/default/v1/champion-chroma-images/16/16024.png",
          "colors": [
            "#27211C",
            "#27211C"
          ],
          "descriptions": [
            {
              "description": null,
              "region": null
            }
          ],
          "rarities": [
            {
              "rarity": null,
              "region": null
            }
          ]
        },
        {
          "name": "Pearl",
          "id": 16025,
          "chromaPath": "http://raw.communitydragon.org/pbe/plugins/rcp-be-lol-game-data/global/default/v1/champion-chroma-images/16/16025.png",
          "colors": [
            "#ECF9F8",
            "#ECF9F8"
          ],
          "descriptions": [
            {
              "description": null,
              "region": null
            }
          ],
          "rarities": [
            {
              "rarity": null,
              "region": null
            }
          ]
        },
        {
          "name": "Peridot",
          "id": 16021,
          "chromaPath": "http://raw.communitydragon.org/pbe/plugins/rcp-be-lol-game-data/global/default/v1/champion-chroma-images/16/16021.png",
          "colors": [
            "#B6E084",
            "#B6E084"
          ],
          "descriptions": [
            {
              "description": null,
              "region": null
            }
          ],
          "rarities": [
            {
              "rarity": null,
              "region": null
            }
          ]
        },
        {
          "name": "Ruby",
          "id": 16019,
          "chromaPath": "http://raw.communitydragon.org/pbe/plugins/rcp-be-lol-game-data/global/default/v1/champion-chroma-images/16/16019.png",
          "colors": [
            "#D33528",
            "#D33528"
          ],
          "descriptions": [
            {
              "description": "This chroma was released as a bundle exclusive in 2021.",
              "region": "riot"
            }
          ],
          "rarities": [
            {
              "rarity": 1,
              "region": "riot"
            }
          ]
        },
        {
          "name": "Sapphire",
          "id": 16022,
          "chromaPath": "http://raw.communitydragon.org/pbe/plugins/rcp-be-lol-game-data/global/default/v1/champion-chroma-images/16/16022.png",
          "colors": [
            "#2756CE",
            "#2756CE"
          ],
          "descriptions": [
            {
              "description": null,
              "region": null
            }
          ],
          "rarities": [
            {
              "rarity": null,
              "region": null
            }
          ]
        },
        {
          "name": "Tanzanite",
          "id": 16023,
          "chromaPath": "http://raw.communitydragon.org/pbe/plugins/rcp-be-lol-game-data/global/default/v1/champion-chroma-images/16/16023.png",
          "colors": [
            "#54209B",
            "#54209B"
          ],
          "descriptions": [
            {
              "description": null,
              "region": null
            }
          ],
          "rarities": [
            {
              "rarity": null,
              "region": null
            }
          ]
        },
        {
          "name": "Turquoise",
          "id": 16026,
          "chromaPath": "http://raw.communitydragon.org/pbe/plugins/rcp-be-lol-game-data/global/default/v1/champion-chroma-images/16/16026.png",
          "colors": [
            "#73BFBE",
            "#73BFBE"
          ],
          "descriptions": [
            {
              "description": null,
              "region": null
            }
          ],
          "rarities": [
            {
              "rarity": null,
              "region": null
            }
          ]
        }
      ],
      "lore": "Good food can be healing, and Soraka works hard to imbue every single pastry she makes with delicious magic that leaves her customers feeling more spritely than when they first walked in. Though her origins are mysterious, the whole cafe agrees: Soraka's work is out of this world!",
      "release": "2021-12-02",
      "set": [
        "Cafe Cuties"
      ],
      "splashPath": "http://raw.communitydragon.org/pbe/plugins/rcp-be-lol-game-data/global/default/v1/champion-splashes/16/16018.jpg",
      "uncenteredSplashPath": "http://raw.communitydragon.org/pbe/plugins/rcp-be-lol-game-data/global/default/v1/champion-splashes/uncentered/16/16018.jpg",
      "tilePath": "http://raw.communitydragon.org/pbe/plugins/rcp-be-lol-game-data/global/default/v1/champion-tiles/16/16018.jpg",
      "loadScreenPath": "https://raw.communitydragon.org/pbe/plugins/rcp-be-lol-game-data/global/default/assets/characters/soraka/skins/skin18/sorakaloadscreen_18.jpg",
      "loadScreenVintagePath": "https://raw.communitydragon.org/pbe/plugins/rcp-be-lol-game-data/global/default/assets/characters/soraka/skins/skin18/sorakaloadscreen_18_le.jpg",
      "newEffects": true,
      "newAnimations": true,
      "newRecall": true,
      "newVoice": false,
      "newQuotes": false,
      "voiceActor": [
        "Lisa Lindsley"
      ],
      "splashArtist": [
        "Ina Wong",
        "West Studio"
      ]
    },
    {
      "name": "Spirit Blossom",
      "id": 16027,
      "isBase": false,
      "availability": "Available",
      "formatName": "Spirit Blossom",
      "lootEligible": true,
      "cost": 1350,
      "sale": 0,
      "distribution": null,
      "rarity": "Epic",
      "chromas": [
        {
          "name": "Citrine",
          "id": 16030,
          "chromaPath": "http://raw.communitydragon.org/pbe/plugins/rcp-be-lol-game-data/global/default/v1/champion-chroma-images/16/16030.png",
          "colors": [
            "#DF9117",
            "#DF9117"
          ],
          "descriptions": [
            {
              "description": null,
              "region": null
            }
          ],
          "rarities": [
            {
              "rarity": null,
              "region": null
            }
          ]
        },
        {
          "name": "Night Blossom",
          "id": 16036,
          "chromaPath": "http://raw.communitydragon.org/pbe/plugins/rcp-be-lol-game-data/global/default/v1/champion-chroma-images/16/16036.png",
          "colors": [
            "#0C0C0F",
            "#B2D1E4"
          ],
          "descriptions": [
            {
              "description": "This chroma was released as a Loot exclusive in the Worlds 2022 event.",
              "region": "riot"
            }
          ],
          "rarities": [
            {
              "rarity": 1,
              "region": "riot"
            }
          ]
        },
        {
          "name": "Obsidian",
          "id": 16035,
          "chromaPath": "http://raw.communitydragon.org/pbe/plugins/rcp-be-lol-game-data/global/default/v1/champion-chroma-images/16/16035.png",
          "colors": [
            "#27211C",
            "#27211C"
          ],
          "descriptions": [
            {
              "description": null,
              "region": null
            }
          ],
          "rarities": [
            {
              "rarity": null,
              "region": null
            }
          ]
        },
        {
          "name": "Pearl",
          "id": 16034,
          "chromaPath": "http://raw.communitydragon.org/pbe/plugins/rcp-be-lol-game-data/global/default/v1/champion-chroma-images/16/16034.png",
          "colors": [
            "#ECF9F8",
            "#ECF9F8"
          ],
          "descriptions": [
            {
              "description": null,
              "region": null
            }
          ],
          "rarities": [
            {
              "rarity": null,
              "region": null
            }
          ]
        },
        {
          "name": "Rose Quartz",
          "id": 16032,
          "chromaPath": "http://raw.communitydragon.org/pbe/plugins/rcp-be-lol-game-data/global/default/v1/champion-chroma-images/16/16032.png",
          "colors": [
            "#E58BA5",
            "#E58BA5"
          ],
          "descriptions": [
            {
              "description": null,
              "region": null
            }
          ],
          "rarities": [
            {
              "rarity": 1,
              "region": "TENCENT"
            }
          ]
        },
        {
          "name": "Ruby",
          "id": 16028,
          "chromaPath": "http://raw.communitydragon.org/pbe/plugins/rcp-be-lol-game-data/global/default/v1/champion-chroma-images/16/16028.png",
          "colors": [
            "#D33528",
            "#D33528"
          ],
          "descriptions": [
            {
              "description": "This chroma was released as a bundle exclusive in 2022.",
              "region": "riot"
            }
          ],
          "rarities": [
            {
              "rarity": 1,
              "region": "riot"
            }
          ]
        },
        {
          "name": "Sapphire",
          "id": 16031,
          "chromaPath": "http://raw.communitydragon.org/pbe/plugins/rcp-be-lol-game-data/global/default/v1/champion-chroma-images/16/16031.png",
          "colors": [
            "#2756CE",
            "#2756CE"
          ],
          "descriptions": [
            {
              "description": null,
              "region": null
            }
          ],
          "rarities": [
            {
              "rarity": null,
              "region": null
            }
          ]
        },
        {
          "name": "Tanzanite",
          "id": 16033,
          "chromaPath": "http://raw.communitydragon.org/pbe/plugins/rcp-be-lol-game-data/global/default/v1/champion-chroma-images/16/16033.png",
          "colors": [
            "#54209B",
            "#54209B"
          ],
          "descriptions": [
            {
              "description": null,
              "region": null
            }
          ],
          "rarities": [
            {
              "rarity": null,
              "region": null
            }
          ]
        },
        {
          "name": "Turquoise",
          "id": 16029,
          "chromaPath": "http://raw.communitydragon.org/pbe/plugins/rcp-be-lol-game-data/global/default/v1/champion-chroma-images/16/16029.png",
          "colors": [
            "#73BFBE",
            "#73BFBE"
          ],
          "descriptions": [
            {
              "description": null,
              "region": null
            }
          ],
          "rarities": [
            {
              "rarity": null,
              "region": null
            }
          ]
        }
      ],
      "lore": "In a secluded corner of the Akana forest, Soraka weeps for those she's lost. Each life cut short she longed to save, but for as many that welcome her as a savior, there are others who see her power as a merciless cruelty. To the Spirit of Pity, death is never a blessing.",
      "release": "2022-10-06",
      "set": [
        "Spirit Blossom"
      ],
      "splashPath": "http://raw.communitydragon.org/pbe/plugins/rcp-be-lol-game-data/global/default/v1/champion-splashes/16/16027.jpg",
      "uncenteredSplashPath": "http://raw.communitydragon.org/pbe/plugins/rcp-be-lol-game-data/global/default/v1/champion-splashes/uncentered/16/16027.jpg",
      "tilePath": "http://raw.communitydragon.org/pbe/plugins/rcp-be-lol-game-data/global/default/v1/champion-tiles/16/16027.jpg",
      "loadScreenPath": "https://raw.communitydragon.org/pbe/plugins/rcp-be-lol-game-data/global/default/assets/characters/soraka/skins/skin27/sorakaloadscreen_27.jpg",
      "loadScreenVintagePath": "https://raw.communitydragon.org/pbe/plugins/rcp-be-lol-game-data/global/default/assets/characters/soraka/skins/skin27/sorakaloadscreen_27_le.jpg",
      "newEffects": true,
      "newAnimations": true,
      "newRecall": true,
      "newVoice": false,
      "newQuotes": false,
      "voiceActor": [
        "Lisa Lindsley"
      ],
      "splashArtist": [
        "Alex 'alexplank' Flores"
      ]
    },
    {
      "name": "Immortal Journey",
      "id": 16037,
      "isBase": false,
      "availability": "Available",
      "formatName": "Immortal Journey",
      "lootEligible": true,
      "cost": 1820,
      "sale": 0,
      "distribution": null,
      "rarity": "Legendary",
      "chromas": [
        {
          "name": "Obsidian",
          "id": 16042,
          "chromaPath": "http://raw.communitydragon.org/pbe/plugins/rcp-be-lol-game-data/global/default/v1/champion-chroma-images/16/16042.png",
          "colors": [
            "#27211C",
            "#27211C"
          ],
          "descriptions": [
            {
              "description": null,
              "region": null
            }
          ],
          "rarities": [
            {
              "rarity": null,
              "region": null
            }
          ]
        },
        {
          "name": "Pearl",
          "id": 16041,
          "chromaPath": "http://raw.communitydragon.org/pbe/plugins/rcp-be-lol-game-data/global/default/v1/champion-chroma-images/16/16041.png",
          "colors": [
            "#ECF9F8",
            "#ECF9F8"
          ],
          "descriptions": [
            {
              "description": null,
              "region": null
            }
          ],
          "rarities": [
            {
              "rarity": null,
              "region": null
            }
          ]
        },
        {
          "name": "Rose Quartz",
          "id": 16039,
          "chromaPath": "http://raw.communitydragon.org/pbe/plugins/rcp-be-lol-game-data/global/default/v1/champion-chroma-images/16/16039.png",
          "colors": [
            "#E58BA5",
            "#E58BA5"
          ],
          "descriptions": [
            {
              "description": null,
              "region": null
            }
          ],
          "rarities": [
            {
              "rarity": 1,
              "region": "TENCENT"
            }
          ]
        },
        {
          "name": "Ruby",
          "id": 16038,
          "chromaPath": "http://raw.communitydragon.org/pbe/plugins/rcp-be-lol-game-data/global/default/v1/champion-chroma-images/16/16038.png",
          "colors": [
            "#D33528",
            "#D33528"
          ],
          "descriptions": [
            {
              "description": "This chroma was released as a bundle exclusive in 2023.",
              "region": "riot"
            }
          ],
          "rarities": [
            {
              "rarity": 1,
              "region": "riot"
            }
          ]
        },
        {
          "name": "Tanzanite",
          "id": 16043,
          "chromaPath": "http://raw.communitydragon.org/pbe/plugins/rcp-be-lol-game-data/global/default/v1/champion-chroma-images/16/16043.png",
          "colors": [
            "#54209B",
            "#54209B"
          ],
          "descriptions": [
            {
              "description": null,
              "region": null
            }
          ],
          "rarities": [
            {
              "rarity": null,
              "region": null
            }
          ]
        },
        {
          "name": "Turquoise",
          "id": 16040,
          "chromaPath": "http://raw.communitydragon.org/pbe/plugins/rcp-be-lol-game-data/global/default/v1/champion-chroma-images/16/16040.png",
          "colors": [
            "#73BFBE",
            "#73BFBE"
          ],
          "descriptions": [
            {
              "description": null,
              "region": null
            }
          ],
          "rarities": [
            {
              "rarity": null,
              "region": null
            }
          ]
        }
      ],
      "lore": "A child of Sprouting Courage School monks, Soraka was expected to follow them, but she hated having the choice already made for her. Remembering the old tales of God Staff Jax, who believed true power came from assuming nothing, Soraka shunned her parents' wishes to train at the Flowing Intuition School. She'll earn immortality her own way.",
      "release": "2023-08-16",
      "set": [
        "Immortal Journey"
      ],
      "splashPath": "http://raw.communitydragon.org/pbe/plugins/rcp-be-lol-game-data/global/default/v1/champion-splashes/16/16037.jpg",
      "uncenteredSplashPath": "http://raw.communitydragon.org/pbe/plugins/rcp-be-lol-game-data/global/default/v1/champion-splashes/uncentered/16/16037.jpg",
      "tilePath": "http://raw.communitydragon.org/pbe/plugins/rcp-be-lol-game-data/global/default/v1/champion-tiles/16/16037.jpg",
      "loadScreenPath": "https://raw.communitydragon.org/pbe/plugins/rcp-be-lol-game-data/global/default/assets/characters/soraka/skins/skin37/sorakaloadscreen_37.jpg",
      "loadScreenVintagePath": "https://raw.communitydragon.org/pbe/plugins/rcp-be-lol-game-data/global/default/assets/characters/soraka/skins/skin37/sorakaloadscreen_37_le.jpg",
      "newEffects": true,
      "newAnimations": true,
      "newRecall": true,
      "newVoice": true,
      "newQuotes": false,
      "voiceActor": [
        "Lisa Lindsley"
      ],
      "splashArtist": [
        "Bo 'chenbowow' Chen"
      ]
    }
  ]
}